task07/task07.v
`timescale 1ns / 1ps

module priority_cd(in, out);  
    parameter IN_WIDTH = 4;
    localparam OUT_WIDTH = $clog2(IN_WIDTH);
    input [IN_WIDTH-1:0] in;
    output [OUT_WIDTH-1:0] out; 
    wire [OUT_WIDTH-1:0] inter [IN_WIDTH:0];
    assign inter[0] = {OUT_WIDTH{1'bX}};
    genvar i, j;
    generate
        for (i = 0; i < IN_WIDTH;i = i + 1) begin 
            assign inter[i + 1] = (in[i]) ? i : inter[i]; 
        end
    endgenerate
    assign out = inter[IN_WIDTH];
endmodule

module priority_cd_tb();
    parameter IN_WIDTH = 64;
    localparam OUT_WIDTH = $clog2(IN_WIDTH);
    reg [IN_WIDTH-1:0] in;
    wire [OUT_WIDTH-1:0] out;

    priority_cd #(.IN_WIDTH(IN_WIDTH)) uut (
        .in(in),
        .out(out)
    );
    initial begin
        $dumpfile("prior.vcd");
        $dumpvars(0, priority_cd_tb);
        in = 0;
        for (in = 0; in <= 100; in = in + 1) begin
            #1;
        end
        $finish;
    end

endmodule

task07/prior.vcd
$date
	Tue Jun 18 22:12:23 2024
$end
$version
	Icarus Verilog
$end
$timescale
	1ps
$end
$scope module priority_cd_tb $end
$var wire 6 ! out [5:0] $end
$var reg 64 " in [63:0] $end
$scope module uut $end
$var wire 64 # in [63:0] $end
$var wire 6 $ out [5:0] $end
$scope begin genblk1[0] $end
$upscope $end
$scope begin genblk1[1] $end
$upscope $end
$scope begin genblk1[2] $end
$upscope $end
$scope begin genblk1[3] $end
$upscope $end
$scope begin genblk1[4] $end
$upscope $end
$scope begin genblk1[5] $end
$upscope $end
$scope begin genblk1[6] $end
$upscope $end
$scope begin genblk1[7] $end
$upscope $end
$scope begin genblk1[8] $end
$upscope $end
$scope begin genblk1[9] $end
$upscope $end
$scope begin genblk1[10] $end
$upscope $end
$scope begin genblk1[11] $end
$upscope $end
$scope begin genblk1[12] $end
$upscope $end
$scope begin genblk1[13] $end
$upscope $end
$scope begin genblk1[14] $end
$upscope $end
$scope begin genblk1[15] $end
$upscope $end
$scope begin genblk1[16] $end
$upscope $end
$scope begin genblk1[17] $end
$upscope $end
$scope begin genblk1[18] $end
$upscope $end
$scope begin genblk1[19] $end
$upscope $end
$scope begin genblk1[20] $end
$upscope $end
$scope begin genblk1[21] $end
$upscope $end
$scope begin genblk1[22] $end
$upscope $end
$scope begin genblk1[23] $end
$upscope $end
$scope begin genblk1[24] $end
$upscope $end
$scope begin genblk1[25] $end
$upscope $end
$scope begin genblk1[26] $end
$upscope $end
$scope begin genblk1[27] $end
$upscope $end
$scope begin genblk1[28] $end
$upscope $end
$scope begin genblk1[29] $end
$upscope $end
$scope begin genblk1[30] $end
$upscope $end
$scope begin genblk1[31] $end
$upscope $end
$scope begin genblk1[32] $end
$upscope $end
$scope begin genblk1[33] $end
$upscope $end
$scope begin genblk1[34] $end
$upscope $end
$scope begin genblk1[35] $end
$upscope $end
$scope begin genblk1[36] $end
$upscope $end
$scope begin genblk1[37] $end
$upscope $end
$scope begin genblk1[38] $end
$upscope $end
$scope begin genblk1[39] $end
$upscope $end
$scope begin genblk1[40] $end
$upscope $end
$scope begin genblk1[41] $end
$upscope $end
$scope begin genblk1[42] $end
$upscope $end
$scope begin genblk1[43] $end
$upscope $end
$scope begin genblk1[44] $end
$upscope $end
$scope begin genblk1[45] $end
$upscope $end
$scope begin genblk1[46] $end
$upscope $end
$scope begin genblk1[47] $end
$upscope $end
$scope begin genblk1[48] $end
$upscope $end
$scope begin genblk1[49] $end
$upscope $end
$scope begin genblk1[50] $end
$upscope $end
$scope begin genblk1[51] $end
$upscope $end
$scope begin genblk1[52] $end
$upscope $end
$scope begin genblk1[53] $end
$upscope $end
$scope begin genblk1[54] $end
$upscope $end
$scope begin genblk1[55] $end
$upscope $end
$scope begin genblk1[56] $end
$upscope $end
$scope begin genblk1[57] $end
$upscope $end
$scope begin genblk1[58] $end
$upscope $end
$scope begin genblk1[59] $end
$upscope $end
$scope begin genblk1[60] $end
$upscope $end
$scope begin genblk1[61] $end
$upscope $end
$scope begin genblk1[62] $end
$upscope $end
$scope begin genblk1[63] $end
$upscope $end
$upscope $end
$upscope $end
$enddefinitions $end
#0
$dumpvars
bx $
b0 #
b0 "
bx !
$end
#1000
b0 !
b0 $
b1 "
b1 #
#2000
b1 !
b1 $
b10 "
b10 #
#3000
b11 "
b11 #
#4000
b10 !
b10 $
b100 "
b100 #
#5000
b101 "
b101 #
#6000
b110 "
b110 #
#7000
b111 "
b111 #
#8000
b11 !
b11 $
b1000 "
b1000 #
#9000
b1001 "
b1001 #
#10000
b1010 "
b1010 #
#11000
b1011 "
b1011 #
#12000
b1100 "
b1100 #
#13000
b1101 "
b1101 #
#14000
b1110 "
b1110 #
#15000
b1111 "
b1111 #
#16000
b100 !
b100 $
b10000 "
b10000 #
#17000
b10001 "
b10001 #
#18000
b10010 "
b10010 #
#19000
b10011 "
b10011 #
#20000
b10100 "
b10100 #
#21000
b10101 "
b10101 #
#22000
b10110 "
b10110 #
#23000
b10111 "
b10111 #
#24000
b11000 "
b11000 #
#25000
b11001 "
b11001 #
#26000
b11010 "
b11010 #
#27000
b11011 "
b11011 #
#28000
b11100 "
b11100 #
#29000
b11101 "
b11101 #
#30000
b11110 "
b11110 #
#31000
b11111 "
b11111 #
#32000
b101 !
b101 $
b100000 "
b100000 #
#33000
b100001 "
b100001 #
#34000
b100010 "
b100010 #
#35000
b100011 "
b100011 #
#36000
b100100 "
b100100 #
#37000
b100101 "
b100101 #
#38000
b100110 "
b100110 #
#39000
b100111 "
b100111 #
#40000
b101000 "
b101000 #
#41000
b101001 "
b101001 #
#42000
b101010 "
b101010 #
#43000
b101011 "
b101011 #
#44000
b101100 "
b101100 #
#45000
b101101 "
b101101 #
#46000
b101110 "
b101110 #
#47000
b101111 "
b101111 #
#48000
b110000 "
b110000 #
#49000
b110001 "
b110001 #
#50000
b110010 "
b110010 #
#51000
b110011 "
b110011 #
#52000
b110100 "
b110100 #
#53000
b110101 "
b110101 #
#54000
b110110 "
b110110 #
#55000
b110111 "
b110111 #
#56000
b111000 "
b111000 #
#57000
b111001 "
b111001 #
#58000
b111010 "
b111010 #
#59000
b111011 "
b111011 #
#60000
b111100 "
b111100 #
#61000
b111101 "
b111101 #
#62000
b111110 "
b111110 #
#63000
b111111 "
b111111 #
#64000
b110 !
b110 $
b1000000 "
b1000000 #
#65000
b1000001 "
b1000001 #
#66000
b1000010 "
b1000010 #
#67000
b1000011 "
b1000011 #
#68000
b1000100 "
b1000100 #
#69000
b1000101 "
b1000101 #
#70000
b1000110 "
b1000110 #
#71000
b1000111 "
b1000111 #
#72000
b1001000 "
b1001000 #
#73000
b1001001 "
b1001001 #
#74000
b1001010 "
b1001010 #
#75000
b1001011 "
b1001011 #
#76000
b1001100 "
b1001100 #
#77000
b1001101 "
b1001101 #
#78000
b1001110 "
b1001110 #
#79000
b1001111 "
b1001111 #
#80000
b1010000 "
b1010000 #
#81000
b1010001 "
b1010001 #
#82000
b1010010 "
b1010010 #
#83000
b1010011 "
b1010011 #
#84000
b1010100 "
b1010100 #
#85000
b1010101 "
b1010101 #
#86000
b1010110 "
b1010110 #
#87000
b1010111 "
b1010111 #
#88000
b1011000 "
b1011000 #
#89000
b1011001 "
b1011001 #
#90000
b1011010 "
b1011010 #
#91000
b1011011 "
b1011011 #
#92000
b1011100 "
b1011100 #
#93000
b1011101 "
b1011101 #
#94000
b1011110 "
b1011110 #
#95000
b1011111 "
b1011111 #
#96000
b1100000 "
b1100000 #
#97000
b1100001 "
b1100001 #
#98000
b1100010 "
b1100010 #
#99000
b1100011 "
b1100011 #
#100000
b1100100 "
b1100100 #
#101000
b1100101 "
b1100101 #
