complex_mul.v
/*
Вход:
A = Ar + jAi
B = Br + jBi
Выход(4 умножения):
Pr = Ar*Br - Ai*Bi
Pi = Ar*Bi + Ai*Br
Выход(3 умножения):
Pr = Ar*(Br+Bi) - (Ar+Ai)*Bi = ArBr + ArBi - ArBi - AiBi = ArBr - AiBi
Pi = Ar*(Br+Bi) + (Ai-Ar)*Br = ArBr + ArBi - ArBr + AiBr = ArBi + AiBr
Используем:
Pr = Ar*(Br+Bi) - (Ar+Ai)*Bi = data1-data2
Pi = Ar*(Br+Bi) + (Ai-Ar)*Br = data1+data3
*/
module complex_mul (
    input signed [7:0] ar,
    input signed [7:0] ai,
    input signed [7:0] br,
    input signed [7:0] bi,

    output reg signed [18:0] pr,
    output reg signed [18:0] pi,
    input clk
);

    reg [2:0] counter = 0;       // счетчик тактов
    reg signed [16:0] data1;     // Ar*(Br+bi)   (сумма 9 бит) * 8 бит => 17 бит
    reg signed [16:0] data2;     // (Ar+Ai)*Bi
    reg signed [16:0] data3;     // (Ai-Ar)*Br

    always @(posedge clk) begin
        counter <= counter + 1;
        case (counter)
            0: begin
                pr <= data1-data2;
                pi <= data1+data3;
                data1 <= (br+bi)*ar;
            end
            1: data2 <= (ar+ai)*bi;
            2: begin
                data3 <= (ai-ar)*br;
                counter <= 0;
            end

        endcase
    end
endmodule

module complex_mul_tb;
    reg signed [7:0] ar;
    reg signed [7:0] ai;
    reg signed [7:0] br;
    reg signed [7:0] bi;
    wire signed [18:0] pr;
    wire signed [18:0] pi;
    reg clk;

    complex_mul dut (
        .ar(ar),
        .ai(ai),
        .br(br),
        .bi(bi),
        .pr(pr),
        .pi(pi),
        .clk(clk)
    );

  initial begin
    $dumpfile("complex_mul.vcd");
    $dumpvars(0, complex_mul_tb);
    clk = 0;
    forever #5 clk = ~clk;
  end

  initial begin
    $display("Ar Ai Br Bi Pr Pi");
    for (ar = -1; ar < 2; ar = ar + 1) begin
        for (ai = -1; ai < 2; ai = ai + 1) begin
            for (br = -1; br < 2; br = br + 1) begin
                for (bi = -1; bi < 2; bi = bi + 1) begin
                    #30;
                    $display("%2d %2d %2d %2d %2d %2d", ar, ai, br, bi, pr, pi);
                end
            end
        end
    end
    #30;
    $display("%2d %2d %2d %2d %2d %2d", ar, ai, br, bi, pr, pi);
    $finish;
  end
endmodule

complex_mul.vcd
$date
	Mon Dec 25 23:25:23 2023
$end
$version
	Icarus Verilog
$end
$timescale
	1s
$end
$scope module complex_mul_tb $end
$var wire 19 ! pr [18:0] $end
$var wire 19 " pi [18:0] $end
$var reg 8 # ai [7:0] $end
$var reg 8 $ ar [7:0] $end
$var reg 8 % bi [7:0] $end
$var reg 8 & br [7:0] $end
$var reg 1 ' clk $end
$scope module dut $end
$var wire 8 ( ai [7:0] $end
$var wire 8 ) ar [7:0] $end
$var wire 8 * bi [7:0] $end
$var wire 8 + br [7:0] $end
$var wire 1 ' clk $end
$var reg 3 , counter [2:0] $end
$var reg 17 - data1 [16:0] $end
$var reg 17 . data2 [16:0] $end
$var reg 17 / data3 [16:0] $end
$var reg 19 0 pi [18:0] $end
$var reg 19 1 pr [18:0] $end
$upscope $end
$upscope $end
$enddefinitions $end
#0
$dumpvars
bx 1
bx 0
bx /
bx .
bx -
b0 ,
b11111111 +
b11111111 *
b11111111 )
b11111111 (
0'
b11111111 &
b11111111 %
b11111111 $
b11111111 #
bx "
bx !
$end
#5
b10 -
b1 ,
1'
#10
0'
#15
b10 .
b10 ,
1'
#20
0'
#25
b0 /
b0 ,
1'
#30
0'
b0 %
b0 *
#35
b1 -
b10 "
b10 0
b0 !
b0 1
b1 ,
1'
#40
0'
#45
b0 .
b10 ,
1'
#50
0'
#55
b0 ,
1'
#60
0'
b1 %
b1 *
#65
b0 -
b1 "
b1 0
b1 !
b1 1
b1 ,
1'
#70
0'
#75
b11111111111111110 .
b10 ,
1'
#80
0'
#85
b0 ,
1'
#90
0'
b0 &
b0 +
b11111111 %
b11111111 *
#95
b1 -
b0 "
b0 0
b10 !
b10 1
b1 ,
1'
#100
0'
#105
b10 .
b10 ,
1'
#110
0'
#115
b0 ,
1'
#120
0'
b0 %
b0 *
#125
b0 -
b1 "
b1 0
b1111111111111111111 !
b1111111111111111111 1
b1 ,
1'
#130
0'
#135
b0 .
b10 ,
1'
#140
0'
#145
b0 ,
1'
#150
0'
b1 %
b1 *
#155
b11111111111111111 -
b0 "
b0 0
b0 !
b0 1
b1 ,
1'
#160
0'
#165
b11111111111111110 .
b10 ,
1'
#170
0'
#175
b0 ,
1'
#180
0'
b1 &
b1 +
b11111111 %
b11111111 *
#185
b0 -
b1111111111111111111 "
b1111111111111111111 0
b1 !
b1 1
b1 ,
1'
#190
0'
#195
b10 .
b10 ,
1'
#200
0'
#205
b0 ,
1'
#210
0'
b0 %
b0 *
#215
b11111111111111111 -
b0 "
b0 0
b1111111111111111110 !
b1111111111111111110 1
b1 ,
1'
#220
0'
#225
b0 .
b10 ,
1'
#230
0'
#235
b0 ,
1'
#240
0'
b1 %
b1 *
#245
b11111111111111110 -
b1111111111111111111 "
b1111111111111111111 0
b1111111111111111111 !
b1111111111111111111 1
b1 ,
1'
#250
0'
#255
b11111111111111110 .
b10 ,
1'
#260
0'
#265
b0 ,
1'
#270
0'
b0 #
b0 (
b11111111 &
b11111111 +
b11111111 %
b11111111 *
#275
b10 -
b1111111111111111110 "
b1111111111111111110 0
b0 !
b0 1
b1 ,
1'
#280
0'
#285
b1 .
b10 ,
1'
#290
0'
#295
b11111111111111111 /
b0 ,
1'
#300
0'
b0 %
b0 *
#305
b1 -
b1 "
b1 0
b1 !
b1 1
b1 ,
1'
#310
0'
#315
b0 .
b10 ,
1'
#320
0'
#325
b0 ,
1'
#330
0'
b1 %
b1 *
#335
b0 -
b0 "
b0 0
b1 ,
1'
#340
0'
#345
b11111111111111111 .
b10 ,
1'
#350
0'
#355
b0 ,
1'
#360
0'
b0 &
b0 +
b11111111 %
b11111111 *
#365
b1 -
b1111111111111111111 "
b1111111111111111111 0
b1 ,
1'
#370
0'
#375
b1 .
b10 ,
1'
#380
0'
#385
b0 /
b0 ,
1'
#390
0'
b0 %
b0 *
#395
b0 -
b1 "
b1 0
b0 !
b0 1
b1 ,
1'
#400
0'
#405
b0 .
b10 ,
1'
#410
0'
#415
b0 ,
1'
#420
0'
b1 %
b1 *
#425
b11111111111111111 -
b0 "
b0 0
b1 ,
1'
#430
0'
#435
b11111111111111111 .
b10 ,
1'
#440
0'
#445
b0 ,
1'
#450
0'
b1 &
b1 +
b11111111 %
b11111111 *
#455
b0 -
b1111111111111111111 "
b1111111111111111111 0
b1 ,
1'
#460
0'
#465
b1 .
b10 ,
1'
#470
0'
#475
b1 /
b0 ,
1'
#480
0'
b0 %
b0 *
#485
b11111111111111111 -
b1 "
b1 0
b1111111111111111111 !
b1111111111111111111 1
b1 ,
1'
#490
0'
#495
b0 .
b10 ,
1'
#500
0'
#505
b0 ,
1'
#510
0'
b1 %
b1 *
#515
b11111111111111110 -
b0 "
b0 0
b1 ,
1'
#520
0'
#525
b11111111111111111 .
b10 ,
1'
#530
0'
#535
b0 ,
1'
#540
0'
b1 #
b1 (
b11111111 &
b11111111 +
b11111111 %
b11111111 *
#545
b10 -
b1111111111111111111 "
b1111111111111111111 0
b1 ,
1'
#550
0'
#555
b0 .
b10 ,
1'
#560
0'
#565
b11111111111111110 /
b0 ,
1'
#570
0'
b0 %
b0 *
#575
b1 -
b0 "
b0 0
b10 !
b10 1
b1 ,
1'
#580
0'
#585
b10 ,
1'
#590
0'
#595
b0 ,
1'
#600
0'
b1 %
b1 *
#605
b0 -
b1111111111111111111 "
b1111111111111111111 0
b1 !
b1 1
b1 ,
1'
#610
0'
#615
b10 ,
1'
#620
0'
#625
b0 ,
1'
#630
0'
b0 &
b0 +
b11111111 %
b11111111 *
#635
b1 -
b1111111111111111110 "
b1111111111111111110 0
b0 !
b0 1
b1 ,
1'
#640
0'
#645
b10 ,
1'
#650
0'
#655
b0 /
b0 ,
1'
#660
0'
b0 %
b0 *
#665
b0 -
b1 "
b1 0
b1 !
b1 1
b1 ,
1'
#670
0'
#675
b10 ,
1'
#680
0'
#685
b0 ,
1'
#690
0'
b1 %
b1 *
#695
b11111111111111111 -
b0 "
b0 0
b0 !
b0 1
b1 ,
1'
#700
0'
#705
b10 ,
1'
#710
0'
#715
b0 ,
1'
#720
0'
b1 &
b1 +
b11111111 %
b11111111 *
#725
b0 -
b1111111111111111111 "
b1111111111111111111 0
b1111111111111111111 !
b1111111111111111111 1
b1 ,
1'
#730
0'
#735
b10 ,
1'
#740
0'
#745
b10 /
b0 ,
1'
#750
0'
b0 %
b0 *
#755
b11111111111111111 -
b10 "
b10 0
b0 !
b0 1
b1 ,
1'
#760
0'
#765
b10 ,
1'
#770
0'
#775
b0 ,
1'
#780
0'
b1 %
b1 *
#785
b11111111111111110 -
b1 "
b1 0
b1111111111111111111 !
b1111111111111111111 1
b1 ,
1'
#790
0'
#795
b10 ,
1'
#800
0'
#805
b0 ,
1'
#810
0'
b0 $
b0 )
b11111111 #
b11111111 (
b11111111 &
b11111111 +
b11111111 %
b11111111 *
#815
b0 -
b0 "
b0 0
b1111111111111111110 !
b1111111111111111110 1
b1 ,
1'
#820
0'
#825
b1 .
b10 ,
1'
#830
0'
#835
b1 /
b0 ,
1'
#840
0'
b0 %
b0 *
#845
b1 "
b1 0
b1111111111111111111 !
b1111111111111111111 1
b1 ,
1'
#850
0'
#855
b0 .
b10 ,
1'
#860
0'
#865
b0 ,
1'
#870
0'
b1 %
b1 *
#875
b0 !
b0 1
b1 ,
1'
#880
0'
#885
b11111111111111111 .
b10 ,
1'
#890
0'
#895
b0 ,
1'
#900
0'
b0 &
b0 +
b11111111 %
b11111111 *
#905
b1 !
b1 1
b1 ,
1'
#910
0'
#915
b1 .
b10 ,
1'
#920
0'
#925
b0 /
b0 ,
1'
#930
0'
b0 %
b0 *
#935
b0 "
b0 0
b1111111111111111111 !
b1111111111111111111 1
b1 ,
1'
#940
0'
#945
b0 .
b10 ,
1'
#950
0'
#955
b0 ,
1'
#960
0'
b1 %
b1 *
#965
b0 !
b0 1
b1 ,
1'
#970
0'
#975
b11111111111111111 .
b10 ,
1'
#980
0'
#985
b0 ,
1'
#990
0'
b1 &
b1 +
b11111111 %
b11111111 *
#995
b1 !
b1 1
b1 ,
1'
#1000
0'
#1005
b1 .
b10 ,
1'
#1010
0'
#1015
b11111111111111111 /
b0 ,
1'
#1020
0'
b0 %
b0 *
#1025
b1111111111111111111 "
b1111111111111111111 0
b1111111111111111111 !
b1111111111111111111 1
b1 ,
1'
#1030
0'
#1035
b0 .
b10 ,
1'
#1040
0'
#1045
b0 ,
1'
#1050
0'
b1 %
b1 *
#1055
b0 !
b0 1
b1 ,
1'
#1060
0'
#1065
b11111111111111111 .
b10 ,
1'
#1070
0'
#1075
b0 ,
1'
#1080
0'
b0 #
b0 (
b11111111 &
b11111111 +
b11111111 %
b11111111 *
#1085
b1 !
b1 1
b1 ,
1'
#1090
0'
#1095
b0 .
b10 ,
1'
#1100
0'
#1105
b0 /
b0 ,
1'
#1110
0'
b0 %
b0 *
#1115
b0 "
b0 0
b0 !
b0 1
b1 ,
1'
#1120
0'
#1125
b10 ,
1'
#1130
0'
#1135
b0 ,
1'
#1140
0'
b1 %
b1 *
#1145
b1 ,
1'
#1150
0'
#1155
b10 ,
1'
#1160
0'
#1165
b0 ,
1'
#1170
0'
b0 &
b0 +
b11111111 %
b11111111 *
#1175
b1 ,
1'
#1180
0'
#1185
b10 ,
1'
#1190
0'
#1195
b0 ,
1'
#1200
0'
b0 %
b0 *
#1205
b1 ,
1'
#1210
0'
#1215
b10 ,
1'
#1220
0'
#1225
b0 ,
1'
#1230
0'
b1 %
b1 *
#1235
b1 ,
1'
#1240
0'
#1245
b10 ,
1'
#1250
0'
#1255
b0 ,
1'
#1260
0'
b1 &
b1 +
b11111111 %
b11111111 *
#1265
b1 ,
1'
#1270
0'
#1275
b10 ,
1'
#1280
0'
#1285
b0 ,
1'
#1290
0'
b0 %
b0 *
#1295
b1 ,
1'
#1300
0'
#1305
b10 ,
1'
#1310
0'
#1315
b0 ,
1'
#1320
0'
b1 %
b1 *
#1325
b1 ,
1'
#1330
0'
#1335
b10 ,
1'
#1340
0'
#1345
b0 ,
1'
#1350
0'
b1 #
b1 (
b11111111 &
b11111111 +
b11111111 %
b11111111 *
#1355
b1 ,
1'
#1360
0'
#1365
b11111111111111111 .
b10 ,
1'
#1370
0'
#1375
b11111111111111111 /
b0 ,
1'
#1380
0'
b0 %
b0 *
#1385
b1111111111111111111 "
b1111111111111111111 0
b1 !
b1 1
b1 ,
1'
#1390
0'
#1395
b0 .
b10 ,
1'
#1400
0'
#1405
b0 ,
1'
#1410
0'
b1 %
b1 *
#1415
b0 !
b0 1
b1 ,
1'
#1420
0'
#1425
b1 .
b10 ,
1'
#1430
0'
#1435
b0 ,
1'
#1440
0'
b0 &
b0 +
b11111111 %
b11111111 *
#1445
b1111111111111111111 !
b1111111111111111111 1
b1 ,
1'
#1450
0'
#1455
b11111111111111111 .
b10 ,
1'
#1460
0'
#1465
b0 /
b0 ,
1'
#1470
0'
b0 %
b0 *
#1475
b0 "
b0 0
b1 !
b1 1
b1 ,
1'
#1480
0'
#1485
b0 .
b10 ,
1'
#1490
0'
#1495
b0 ,
1'
#1500
0'
b1 %
b1 *
#1505
b0 !
b0 1
b1 ,
1'
#1510
0'
#1515
b1 .
b10 ,
1'
#1520
0'
#1525
b0 ,
1'
#1530
0'
b1 &
b1 +
b11111111 %
b11111111 *
#1535
b1111111111111111111 !
b1111111111111111111 1
b1 ,
1'
#1540
0'
#1545
b11111111111111111 .
b10 ,
1'
#1550
0'
#1555
b1 /
b0 ,
1'
#1560
0'
b0 %
b0 *
#1565
b1 "
b1 0
b1 !
b1 1
b1 ,
1'
#1570
0'
#1575
b0 .
b10 ,
1'
#1580
0'
#1585
b0 ,
1'
#1590
0'
b1 %
b1 *
#1595
b0 !
b0 1
b1 ,
1'
#1600
0'
#1605
b1 .
b10 ,
1'
#1610
0'
#1615
b0 ,
1'
#1620
0'
b1 $
b1 )
b11111111 #
b11111111 (
b11111111 &
b11111111 +
b11111111 %
b11111111 *
#1625
b11111111111111110 -
b1111111111111111111 !
b1111111111111111111 1
b1 ,
1'
#1630
0'
#1635
b0 .
b10 ,
1'
#1640
0'
#1645
b10 /
b0 ,
1'
#1650
0'
b0 %
b0 *
#1655
b11111111111111111 -
b0 "
b0 0
b1111111111111111110 !
b1111111111111111110 1
b1 ,
1'
#1660
0'
#1665
b10 ,
1'
#1670
0'
#1675
b0 ,
1'
#1680
0'
b1 %
b1 *
#1685
b0 -
b1 "
b1 0
b1111111111111111111 !
b1111111111111111111 1
b1 ,
1'
#1690
0'
#1695
b10 ,
1'
#1700
0'
#1705
b0 ,
1'
#1710
0'
b0 &
b0 +
b11111111 %
b11111111 *
#1715
b11111111111111111 -
b10 "
b10 0
b0 !
b0 1
b1 ,
1'
#1720
0'
#1725
b10 ,
1'
#1730
0'
#1735
b0 /
b0 ,
1'
#1740
0'
b0 %
b0 *
#1745
b0 -
b1111111111111111111 "
b1111111111111111111 0
b1111111111111111111 !
b1111111111111111111 1
b1 ,
1'
#1750
0'
#1755
b10 ,
1'
#1760
0'
#1765
b0 ,
1'
#1770
0'
b1 %
b1 *
#1775
b1 -
b0 "
b0 0
b0 !
b0 1
b1 ,
1'
#1780
0'
#1785
b10 ,
1'
#1790
0'
#1795
b0 ,
1'
#1800
0'
b1 &
b1 +
b11111111 %
b11111111 *
#1805
b0 -
b1 "
b1 0
b1 !
b1 1
b1 ,
1'
#1810
0'
#1815
b10 ,
1'
#1820
0'
#1825
b11111111111111110 /
b0 ,
1'
#1830
0'
b0 %
b0 *
#1835
b1 -
b1111111111111111110 "
b1111111111111111110 0
b0 !
b0 1
b1 ,
1'
#1840
0'
#1845
b10 ,
1'
#1850
0'
#1855
b0 ,
1'
#1860
0'
b1 %
b1 *
#1865
b10 -
b1111111111111111111 "
b1111111111111111111 0
b1 !
b1 1
b1 ,
1'
#1870
0'
#1875
b10 ,
1'
#1880
0'
#1885
b0 ,
1'
#1890
0'
b0 #
b0 (
b11111111 &
b11111111 +
b11111111 %
b11111111 *
#1895
b11111111111111110 -
b0 "
b0 0
b10 !
b10 1
b1 ,
1'
#1900
0'
#1905
b11111111111111111 .
b10 ,
1'
#1910
0'
#1915
b1 /
b0 ,
1'
#1920
0'
b0 %
b0 *
#1925
b11111111111111111 -
b1111111111111111111 "
b1111111111111111111 0
b1111111111111111111 !
b1111111111111111111 1
b1 ,
1'
#1930
0'
#1935
b0 .
b10 ,
1'
#1940
0'
#1945
b0 ,
1'
#1950
0'
b1 %
b1 *
#1955
b0 -
b0 "
b0 0
b1 ,
1'
#1960
0'
#1965
b1 .
b10 ,
1'
#1970
0'
#1975
b0 ,
1'
#1980
0'
b0 &
b0 +
b11111111 %
b11111111 *
#1985
b11111111111111111 -
b1 "
b1 0
b1 ,
1'
#1990
0'
#1995
b11111111111111111 .
b10 ,
1'
#2000
0'
#2005
b0 /
b0 ,
1'
#2010
0'
b0 %
b0 *
#2015
b0 -
b1111111111111111111 "
b1111111111111111111 0
b0 !
b0 1
b1 ,
1'
#2020
0'
#2025
b0 .
b10 ,
1'
#2030
0'
#2035
b0 ,
1'
#2040
0'
b1 %
b1 *
#2045
b1 -
b0 "
b0 0
b1 ,
1'
#2050
0'
#2055
b1 .
b10 ,
1'
#2060
0'
#2065
b0 ,
1'
#2070
0'
b1 &
b1 +
b11111111 %
b11111111 *
#2075
b0 -
b1 "
b1 0
b1 ,
1'
#2080
0'
#2085
b11111111111111111 .
b10 ,
1'
#2090
0'
#2095
b11111111111111111 /
b0 ,
1'
#2100
0'
b0 %
b0 *
#2105
b1 -
b1111111111111111111 "
b1111111111111111111 0
b1 !
b1 1
b1 ,
1'
#2110
0'
#2115
b0 .
b10 ,
1'
#2120
0'
#2125
b0 ,
1'
#2130
0'
b1 %
b1 *
#2135
b10 -
b0 "
b0 0
b1 ,
1'
#2140
0'
#2145
b1 .
b10 ,
1'
#2150
0'
#2155
b0 ,
1'
#2160
0'
b1 #
b1 (
b11111111 &
b11111111 +
b11111111 %
b11111111 *
#2165
b11111111111111110 -
b1 "
b1 0
b1 ,
1'
#2170
0'
#2175
b11111111111111110 .
b10 ,
1'
#2180
0'
#2185
b0 /
b0 ,
1'
#2190
0'
b0 %
b0 *
#2195
b11111111111111111 -
b1111111111111111110 "
b1111111111111111110 0
b0 !
b0 1
b1 ,
1'
#2200
0'
#2205
b0 .
b10 ,
1'
#2210
0'
#2215
b0 ,
1'
#2220
0'
b1 %
b1 *
#2225
b0 -
b1111111111111111111 "
b1111111111111111111 0
b1111111111111111111 !
b1111111111111111111 1
b1 ,
1'
#2230
0'
#2235
b10 .
b10 ,
1'
#2240
0'
#2245
b0 ,
1'
#2250
0'
b0 &
b0 +
b11111111 %
b11111111 *
#2255
b11111111111111111 -
b0 "
b0 0
b1111111111111111110 !
b1111111111111111110 1
b1 ,
1'
#2260
0'
#2265
b11111111111111110 .
b10 ,
1'
#2270
0'
#2275
b0 ,
1'
#2280
0'
b0 %
b0 *
#2285
b0 -
b1111111111111111111 "
b1111111111111111111 0
b1 !
b1 1
b1 ,
1'
#2290
0'
#2295
b0 .
b10 ,
1'
#2300
0'
#2305
b0 ,
1'
#2310
0'
b1 %
b1 *
#2315
b1 -
b0 "
b0 0
b0 !
b0 1
b1 ,
1'
#2320
0'
#2325
b10 .
b10 ,
1'
#2330
0'
#2335
b0 ,
1'
#2340
0'
b1 &
b1 +
b11111111 %
b11111111 *
#2345
b0 -
b1 "
b1 0
b1111111111111111111 !
b1111111111111111111 1
b1 ,
1'
#2350
0'
#2355
b11111111111111110 .
b10 ,
1'
#2360
0'
#2365
b0 ,
1'
#2370
0'
b0 %
b0 *
#2375
b1 -
b0 "
b0 0
b10 !
b10 1
b1 ,
1'
#2380
0'
#2385
b0 .
b10 ,
1'
#2390
0'
#2395
b0 ,
1'
#2400
0'
b1 %
b1 *
#2405
b10 -
b1 "
b1 0
b1 !
b1 1
b1 ,
1'
#2410
0'
#2415
b10 .
b10 ,
1'
#2420
0'
#2425
b0 ,
1'
#2430
0'
b10 $
b10 )
b10 #
b10 (
b10 &
b10 +
b10 %
b10 *
#2435
b1000 -
b10 "
b10 0
b0 !
b0 1
b1 ,
1'
#2440
0'
#2445
b1000 .
b10 ,
1'
#2450
0'
#2455
b0 ,
1'
