number7.v
`timescale 1ns / 1ps

module priority_cd(in, out);  
    parameter IN_WIDTH = 4;
    localparam OUT_WIDTH = $clog2(IN_WIDTH);
    input [IN_WIDTH-1:0] in;
    output [OUT_WIDTH-1:0] out; 
    wire [OUT_WIDTH-1:0] inter [IN_WIDTH:0];
    assign inter[0] = {OUT_WIDTH{1'bX}};
    genvar i, j;
    generate
        for (i = 0; i < IN_WIDTH;i = i + 1) begin 
            assign inter[i + 1] = (in[i]) ? i : inter[i]; 
        end
    endgenerate
    assign out = inter[IN_WIDTH];
endmodule

module priority_cd_tb();
    parameter IN_WIDTH = 8;
    localparam OUT_WIDTH = $clog2(IN_WIDTH);
    reg [IN_WIDTH-1:0] in;
    wire [OUT_WIDTH-1:0] out;

    priority_cd #(.IN_WIDTH(IN_WIDTH)) uut (
        .in(in),
        .out(out)
    );
    initial begin
        $dumpfile("prior.vcd");
        $dumpvars(0, priority_cd_tb);
        #800 
        $finish;
        in = 0;
        always #10 in = in + 1;
    end

endmodule

dump.vcd
$date
	Mon Jun 17 22:21:40 2024
$end
$version
	Icarus Verilog
$end
$timescale
	1ps
$end
$scope module priority_cd_tb $end
$var wire 3 ! out [2:0] $end
$var reg 8 " in [7:0] $end
$scope module uut $end
$var wire 8 # in [7:0] $end
$var wire 3 $ out [2:0] $end
$scope begin genblk1[0] $end
$upscope $end
$scope begin genblk1[1] $end
$upscope $end
$scope begin genblk1[2] $end
$upscope $end
$scope begin genblk1[3] $end
$upscope $end
$scope begin genblk1[4] $end
$upscope $end
$scope begin genblk1[5] $end
$upscope $end
$scope begin genblk1[6] $end
$upscope $end
$scope begin genblk1[7] $end
$upscope $end
$upscope $end
$upscope $end
$enddefinitions $end
#0
$dumpvars
bx $
b0 #
b0 "
bx !
$end
#1000
b0 !
b0 $
b1 "
b1 #
#2000
b1 !
b1 $
b10 "
b10 #
#3000
b11 "
b11 #
#4000
b10 !
b10 $
b100 "
b100 #
#5000
b101 "
b101 #
#6000
b110 "
b110 #
#7000
b111 "
b111 #
#8000
b11 !
b11 $
b1000 "
b1000 #
#9000
b1001 "
b1001 #
#10000
b1010 "
b1010 #
#11000
b1011 "
b1011 #
#12000
b1100 "
b1100 #
#13000
b1101 "
b1101 #
#14000
b1110 "
b1110 #
#15000
b1111 "
b1111 #
#16000
b100 !
b100 $
b10000 "
b10000 #
#17000
b10001 "
b10001 #
#18000
b10010 "
b10010 #
#19000
b10011 "
b10011 #
#20000
b10100 "
b10100 #
#21000
b10101 "
b10101 #
#22000
b10110 "
b10110 #
#23000
b10111 "
b10111 #
#24000
b11000 "
b11000 #
#25000
b11001 "
b11001 #
#26000
b11010 "
b11010 #
#27000
b11011 "
b11011 #
#28000
b11100 "
b11100 #
#29000
b11101 "
b11101 #
#30000
b11110 "
b11110 #
#31000
b11111 "
b11111 #
#32000
b101 !
b101 $
b100000 "
b100000 #
#33000
b100001 "
b100001 #
#34000
b100010 "
b100010 #
#35000
b100011 "
b100011 #
#36000
b100100 "
b100100 #
#37000
b100101 "
b100101 #
#38000
b100110 "
b100110 #
#39000
b100111 "
b100111 #
#40000
b101000 "
b101000 #
#41000
b101001 "
b101001 #
#42000
b101010 "
b101010 #
#43000
b101011 "
b101011 #
#44000
b101100 "
b101100 #
#45000
b101101 "
b101101 #
#46000
b101110 "
b101110 #
#47000
b101111 "
b101111 #
#48000
b110000 "
b110000 #
#49000
b110001 "
b110001 #
#50000
b110010 "
b110010 #
#51000
b110011 "
b110011 #
#52000
b110100 "
b110100 #
#53000
b110101 "
b110101 #
#54000
b110110 "
b110110 #
#55000
b110111 "
b110111 #
#56000
b111000 "
b111000 #
#57000
b111001 "
b111001 #
#58000
b111010 "
b111010 #
#59000
b111011 "
b111011 #
#60000
b111100 "
b111100 #
#61000
b111101 "
b111101 #
#62000
b111110 "
b111110 #
#63000
b111111 "
b111111 #
#64000
b110 !
b110 $
b1000000 "
b1000000 #
#65000
b1000001 "
b1000001 #
#66000
b1000010 "
b1000010 #
#67000
b1000011 "
b1000011 #
#68000
b1000100 "
b1000100 #
#69000
b1000101 "
b1000101 #
#70000
b1000110 "
b1000110 #
#71000
b1000111 "
b1000111 #
#72000
b1001000 "
b1001000 #
#73000
b1001001 "
b1001001 #
#74000
b1001010 "
b1001010 #
#75000
b1001011 "
b1001011 #
#76000
b1001100 "
b1001100 #
#77000
b1001101 "
b1001101 #
#78000
b1001110 "
b1001110 #
#79000
b1001111 "
b1001111 #
#80000
b1010000 "
b1010000 #
#81000
b1010001 "
b1010001 #
#82000
b1010010 "
b1010010 #
#83000
b1010011 "
b1010011 #
#84000
b1010100 "
b1010100 #
#85000
b1010101 "
b1010101 #
#86000
b1010110 "
b1010110 #
#87000
b1010111 "
b1010111 #
#88000
b1011000 "
b1011000 #
#89000
b1011001 "
b1011001 #
#90000
b1011010 "
b1011010 #
#91000
b1011011 "
b1011011 #
#92000
b1011100 "
b1011100 #
#93000
b1011101 "
b1011101 #
#94000
b1011110 "
b1011110 #
#95000
b1011111 "
b1011111 #
#96000
b1100000 "
b1100000 #
#97000
b1100001 "
b1100001 #
#98000
b1100010 "
b1100010 #
#99000
b1100011 "
b1100011 #
#100000
b1100100 "
b1100100 #
#101000
b1100101 "
b1100101 #
#102000
b1100110 "
b1100110 #
#103000
b1100111 "
b1100111 #
#104000
b1101000 "
b1101000 #
#105000
b1101001 "
b1101001 #
#106000
b1101010 "
b1101010 #
#107000
b1101011 "
b1101011 #
#108000
b1101100 "
b1101100 #
#109000
b1101101 "
b1101101 #
#110000
b1101110 "
b1101110 #
#111000
b1101111 "
b1101111 #
#112000
b1110000 "
b1110000 #
#113000
b1110001 "
b1110001 #
#114000
b1110010 "
b1110010 #
#115000
b1110011 "
b1110011 #
#116000
b1110100 "
b1110100 #
#117000
b1110101 "
b1110101 #
#118000
b1110110 "
b1110110 #
#119000
b1110111 "
b1110111 #
#120000
b1111000 "
b1111000 #
#121000
b1111001 "
b1111001 #
#122000
b1111010 "
b1111010 #
#123000
b1111011 "
b1111011 #
#124000
b1111100 "
b1111100 #
#125000
b1111101 "
b1111101 #
#126000
b1111110 "
b1111110 #
#127000
b1111111 "
b1111111 #
#128000
b111 !
b111 $
b10000000 "
b10000000 #
#129000
b10000001 "
b10000001 #
#130000
b10000010 "
b10000010 #
#131000
b10000011 "
b10000011 #
#132000
b10000100 "
b10000100 #
#133000
b10000101 "
b10000101 #
#134000
b10000110 "
b10000110 #
#135000
b10000111 "
b10000111 #
#136000
b10001000 "
b10001000 #
#137000
b10001001 "
b10001001 #
#138000
b10001010 "
b10001010 #
#139000
b10001011 "
b10001011 #
#140000
b10001100 "
b10001100 #
#141000
b10001101 "
b10001101 #
#142000
b10001110 "
b10001110 #
#143000
b10001111 "
b10001111 #
#144000
b10010000 "
b10010000 #
#145000
b10010001 "
b10010001 #
#146000
b10010010 "
b10010010 #
#147000
b10010011 "
b10010011 #
#148000
b10010100 "
b10010100 #
#149000
b10010101 "
b10010101 #
#150000
b10010110 "
b10010110 #
#151000
b10010111 "
b10010111 #
#152000
b10011000 "
b10011000 #
#153000
b10011001 "
b10011001 #
#154000
b10011010 "
b10011010 #
#155000
b10011011 "
b10011011 #
#156000
b10011100 "
b10011100 #
#157000
b10011101 "
b10011101 #
#158000
b10011110 "
b10011110 #
#159000
b10011111 "
b10011111 #
#160000
b10100000 "
b10100000 #
#161000
b10100001 "
b10100001 #
#162000
b10100010 "
b10100010 #
#163000
b10100011 "
b10100011 #
#164000
b10100100 "
b10100100 #
#165000
b10100101 "
b10100101 #
#166000
b10100110 "
b10100110 #
#167000
b10100111 "
b10100111 #
#168000
b10101000 "
b10101000 #
#169000
b10101001 "
b10101001 #
#170000
b10101010 "
b10101010 #
#171000
b10101011 "
b10101011 #
#172000
b10101100 "
b10101100 #
#173000
b10101101 "
b10101101 #
#174000
b10101110 "
b10101110 #
#175000
b10101111 "
b10101111 #
#176000
b10110000 "
b10110000 #
#177000
b10110001 "
b10110001 #
#178000
b10110010 "
b10110010 #
#179000
b10110011 "
b10110011 #
#180000
b10110100 "
b10110100 #
#181000
b10110101 "
b10110101 #
#182000
b10110110 "
b10110110 #
#183000
b10110111 "
b10110111 #
#184000
b10111000 "
b10111000 #
#185000
b10111001 "
b10111001 #
#186000
b10111010 "
b10111010 #
#187000
b10111011 "
b10111011 #
#188000
b10111100 "
b10111100 #
#189000
b10111101 "
b10111101 #
#190000
b10111110 "
b10111110 #
#191000
b10111111 "
b10111111 #
#192000
b11000000 "
b11000000 #
#193000
b11000001 "
b11000001 #
#194000
b11000010 "
b11000010 #
#195000
b11000011 "
b11000011 #
#196000
b11000100 "
b11000100 #
#197000
b11000101 "
b11000101 #
#198000
b11000110 "
b11000110 #
#199000
b11000111 "
b11000111 #
#200000
b11001000 "
b11001000 #
#201000
b11001001 "
b11001001 #
#202000
b11001010 "
b11001010 #
#203000
b11001011 "
b11001011 #
#204000
b11001100 "
b11001100 #
#205000
b11001101 "
b11001101 #
#206000
b11001110 "
b11001110 #
#207000
b11001111 "
b11001111 #
#208000
b11010000 "
b11010000 #
#209000
b11010001 "
b11010001 #
#210000
b11010010 "
b11010010 #
#211000
b11010011 "
b11010011 #
#212000
b11010100 "
b11010100 #
#213000
b11010101 "
b11010101 #
#214000
b11010110 "
b11010110 #
#215000
b11010111 "
b11010111 #
#216000
b11011000 "
b11011000 #
#217000
b11011001 "
b11011001 #
#218000
b11011010 "
b11011010 #
#219000
b11011011 "
b11011011 #
#220000
b11011100 "
b11011100 #
#221000
b11011101 "
b11011101 #
#222000
b11011110 "
b11011110 #
#223000
b11011111 "
b11011111 #
#224000
b11100000 "
b11100000 #
#225000
b11100001 "
b11100001 #
#226000
b11100010 "
b11100010 #
#227000
b11100011 "
b11100011 #
#228000
b11100100 "
b11100100 #
#229000
b11100101 "
b11100101 #
#230000
b11100110 "
b11100110 #
#231000
b11100111 "
b11100111 #
#232000
b11101000 "
b11101000 #
#233000
b11101001 "
b11101001 #
#234000
b11101010 "
b11101010 #
#235000
b11101011 "
b11101011 #
#236000
b11101100 "
b11101100 #
#237000
b11101101 "
b11101101 #
#238000
b11101110 "
b11101110 #
#239000
b11101111 "
b11101111 #
#240000
b11110000 "
b11110000 #
#241000
b11110001 "
b11110001 #
#242000
b11110010 "
b11110010 #
#243000
b11110011 "
b11110011 #
#244000
b11110100 "
b11110100 #
#245000
b11110101 "
b11110101 #
#246000
b11110110 "
b11110110 #
#247000
b11110111 "
b11110111 #
#248000
b11111000 "
b11111000 #
#249000
b11111001 "
b11111001 #
#250000
b11111010 "
b11111010 #
#251000
b11111011 "
b11111011 #
#252000
b11111100 "
b11111100 #
#253000
b11111101 "
b11111101 #
#254000
b11111110 "
b11111110 #
#255000
b11111111 "
b11111111 #
#256000
bx !
bx $
b0 "
b0 #
#257000
b0 !
b0 $
b1 "
b1 #
#258000
b1 !
b1 $
b10 "
b10 #
#259000
b11 "
b11 #
#260000
b10 !
b10 $
b100 "
b100 #
#261000
b101 "
b101 #
#262000
b110 "
b110 #
#263000
b111 "
b111 #
#264000
b11 !
b11 $
b1000 "
b1000 #
#265000
b1001 "
b1001 #
#266000
b1010 "
b1010 #
#267000
b1011 "
b1011 #
#268000
b1100 "
b1100 #
#269000
b1101 "
b1101 #
#270000
b1110 "
b1110 #
#271000
b1111 "
b1111 #
#272000
b100 !
b100 $
b10000 "
b10000 #
#273000
b10001 "
b10001 #
#274000
b10010 "
b10010 #
#275000
b10011 "
b10011 #
#276000
b10100 "
b10100 #
#277000
b10101 "
b10101 #
#278000
b10110 "
b10110 #
#279000
b10111 "
b10111 #
#280000
b11000 "
b11000 #
#281000
b11001 "
b11001 #
#282000
b11010 "
b11010 #
#283000
b11011 "
b11011 #
#284000
b11100 "
b11100 #
#285000
b11101 "
b11101 #
#286000
b11110 "
b11110 #
#287000
b11111 "
b11111 #
#288000
b101 !
b101 $
b100000 "
b100000 #
#289000
b100001 "
b100001 #
#290000
b100010 "
b100010 #
#291000
b100011 "
b100011 #
#292000
b100100 "
b100100 #
#293000
b100101 "
b100101 #
#294000
b100110 "
b100110 #
#295000
b100111 "
b100111 #
#296000
b101000 "
b101000 #
#297000
b101001 "
b101001 #
#298000
b101010 "
b101010 #
#299000
b101011 "
b101011 #
#300000
b101100 "
b101100 #
#301000
b101101 "
b101101 #
#302000
b101110 "
b101110 #
#303000
b101111 "
b101111 #
#304000
b110000 "
b110000 #
#305000
b110001 "
b110001 #
#306000
b110010 "
b110010 #
#307000
b110011 "
b110011 #
#308000
b110100 "
b110100 #
#309000
b110101 "
b110101 #
#310000
b110110 "
b110110 #
#311000
b110111 "
b110111 #
#312000
b111000 "
b111000 #
#313000
b111001 "
b111001 #
#314000
b111010 "
b111010 #
#315000
b111011 "
b111011 #
#316000
b111100 "
b111100 #
#317000
b111101 "
b111101 #
#318000
b111110 "
b111110 #
#319000
b111111 "
b111111 #
#320000
b110 !
b110 $
b1000000 "
b1000000 #
#321000
b1000001 "
b1000001 #
#322000
b1000010 "
b1000010 #
#323000
b1000011 "
b1000011 #
#324000
b1000100 "
b1000100 #
#325000
b1000101 "
b1000101 #
#326000
b1000110 "
b1000110 #
#327000
b1000111 "
b1000111 #
#328000
b1001000 "
b1001000 #
#329000
b1001001 "
b1001001 #
#330000
b1001010 "
b1001010 #
#331000
b1001011 "
b1001011 #
#332000
b1001100 "
b1001100 #
#333000
b1001101 "
b1001101 #
#334000
b1001110 "
b1001110 #
#335000
b1001111 "
b1001111 #
#336000
b1010000 "
b1010000 #
#337000
b1010001 "
b1010001 #
#338000
b1010010 "
b1010010 #
#339000
b1010011 "
b1010011 #
#340000
b1010100 "
b1010100 #
#341000
b1010101 "
b1010101 #
#342000
b1010110 "
b1010110 #
#343000
b1010111 "
b1010111 #
#344000
b1011000 "
b1011000 #
#345000
b1011001 "
b1011001 #
#346000
b1011010 "
b1011010 #
#347000
b1011011 "
b1011011 #
#348000
b1011100 "
b1011100 #
#349000
b1011101 "
b1011101 #
#350000
b1011110 "
b1011110 #
#351000
b1011111 "
b1011111 #
#352000
b1100000 "
b1100000 #
#353000
b1100001 "
b1100001 #
#354000
b1100010 "
b1100010 #
#355000
b1100011 "
b1100011 #
#356000
b1100100 "
b1100100 #
#357000
b1100101 "
b1100101 #
#358000
b1100110 "
b1100110 #
#359000
b1100111 "
b1100111 #
#360000
b1101000 "
b1101000 #
#361000
b1101001 "
b1101001 #
#362000
b1101010 "
b1101010 #
#363000
b1101011 "
b1101011 #
#364000
b1101100 "
b1101100 #
#365000
b1101101 "
b1101101 #
#366000
b1101110 "
b1101110 #
#367000
b1101111 "
b1101111 #
#368000
b1110000 "
b1110000 #
#369000
b1110001 "
b1110001 #
#370000
b1110010 "
b1110010 #
#371000
b1110011 "
b1110011 #
#372000
b1110100 "
b1110100 #
#373000
b1110101 "
b1110101 #
#374000
b1110110 "
b1110110 #
#375000
b1110111 "
b1110111 #
#376000
b1111000 "
b1111000 #
#377000
b1111001 "
b1111001 #
#378000
b1111010 "
b1111010 #
#379000
b1111011 "
b1111011 #
#380000
b1111100 "
b1111100 #
#381000
b1111101 "
b1111101 #
#382000
b1111110 "
b1111110 #
#383000
b1111111 "
b1111111 #
#384000
b111 !
b111 $
b10000000 "
b10000000 #
#385000
b10000001 "
b10000001 #
#386000
b10000010 "
b10000010 #
#387000
b10000011 "
b10000011 #
#388000
b10000100 "
b10000100 #
#389000
b10000101 "
b10000101 #
#390000
b10000110 "
b10000110 #
#391000
b10000111 "
b10000111 #
#392000
b10001000 "
b10001000 #
#393000
b10001001 "
b10001001 #
#394000
b10001010 "
b10001010 #
#395000
b10001011 "
b10001011 #
#396000
b10001100 "
b10001100 #
#397000
b10001101 "
b10001101 #
#398000
b10001110 "
b10001110 #
#399000
b10001111 "
b10001111 #
#400000
b10010000 "
b10010000 #
#401000
b10010001 "
b10010001 #
#402000
b10010010 "
b10010010 #
#403000
b10010011 "
b10010011 #
#404000
b10010100 "
b10010100 #
#405000
b10010101 "
b10010101 #
#406000
b10010110 "
b10010110 #
#407000
b10010111 "
b10010111 #
#408000
b10011000 "
b10011000 #
#409000
b10011001 "
b10011001 #
#410000
b10011010 "
b10011010 #
#411000
b10011011 "
b10011011 #
#412000
b10011100 "
b10011100 #
#413000
b10011101 "
b10011101 #
#414000
b10011110 "
b10011110 #
#415000
b10011111 "
b10011111 #
#416000
b10100000 "
b10100000 #
#417000
b10100001 "
b10100001 #
#418000
b10100010 "
b10100010 #
#419000
b10100011 "
b10100011 #
#420000
b10100100 "
b10100100 #
#421000
b10100101 "
b10100101 #
#422000
b10100110 "
b10100110 #
#423000
b10100111 "
b10100111 #
#424000
b10101000 "
b10101000 #
#425000
b10101001 "
b10101001 #
#426000
b10101010 "
b10101010 #
#427000
b10101011 "
b10101011 #
#428000
b10101100 "
b10101100 #
#429000
b10101101 "
b10101101 #
#430000
b10101110 "
b10101110 #
#431000
b10101111 "
b10101111 #
#432000
b10110000 "
b10110000 #
#433000
b10110001 "
b10110001 #
#434000
b10110010 "
b10110010 #
#435000
b10110011 "
b10110011 #
#436000
b10110100 "
b10110100 #
#437000
b10110101 "
b10110101 #
#438000
b10110110 "
b10110110 #
#439000
b10110111 "
b10110111 #
#440000
b10111000 "
b10111000 #
#441000
b10111001 "
b10111001 #
#442000
b10111010 "
b10111010 #
#443000
b10111011 "
b10111011 #
#444000
b10111100 "
b10111100 #
#445000
b10111101 "
b10111101 #
#446000
b10111110 "
b10111110 #
#447000
b10111111 "
b10111111 #
#448000
b11000000 "
b11000000 #
#449000
b11000001 "
b11000001 #
#450000
b11000010 "
b11000010 #
#451000
b11000011 "
b11000011 #
#452000
b11000100 "
b11000100 #
#453000
b11000101 "
b11000101 #
#454000
b11000110 "
b11000110 #
#455000
b11000111 "
b11000111 #
#456000
b11001000 "
b11001000 #
#457000
b11001001 "
b11001001 #
#458000
b11001010 "
b11001010 #
#459000
b11001011 "
b11001011 #
#460000
b11001100 "
b11001100 #
#461000
b11001101 "
b11001101 #
#462000
b11001110 "
b11001110 #
#463000
b11001111 "
b11001111 #
#464000
b11010000 "
b11010000 #
#465000
b11010001 "
b11010001 #
#466000
b11010010 "
b11010010 #
#467000
b11010011 "
b11010011 #
#468000
b11010100 "
b11010100 #
#469000
b11010101 "
b11010101 #
#470000
b11010110 "
b11010110 #
#471000
b11010111 "
b11010111 #
#472000
b11011000 "
b11011000 #
#473000
b11011001 "
b11011001 #
#474000
b11011010 "
b11011010 #
#475000
b11011011 "
b11011011 #
#476000
b11011100 "
b11011100 #
#477000
b11011101 "
b11011101 #
#478000
b11011110 "
b11011110 #
#479000
b11011111 "
b11011111 #
#480000
b11100000 "
b11100000 #
#481000
b11100001 "
b11100001 #
#482000
b11100010 "
b11100010 #
#483000
b11100011 "
b11100011 #
#484000
b11100100 "
b11100100 #
#485000
b11100101 "
b11100101 #
#486000
b11100110 "
b11100110 #
#487000
b11100111 "
b11100111 #
#488000
b11101000 "
b11101000 #
#489000
b11101001 "
b11101001 #
#490000
b11101010 "
b11101010 #
#491000
b11101011 "
b11101011 #
#492000
b11101100 "
b11101100 #
#493000
b11101101 "
b11101101 #
#494000
b11101110 "
b11101110 #
#495000
b11101111 "
b11101111 #
#496000
b11110000 "
b11110000 #
#497000
b11110001 "
b11110001 #
#498000
b11110010 "
b11110010 #
#499000
b11110011 "
b11110011 #
#500000
b11110100 "
b11110100 #
#501000
b11110101 "
b11110101 #
#502000
b11110110 "
b11110110 #
#503000
b11110111 "
b11110111 #
#504000
b11111000 "
b11111000 #
#505000
b11111001 "
b11111001 #
#506000
b11111010 "
b11111010 #
#507000
b11111011 "
b11111011 #
#508000
b11111100 "
b11111100 #
#509000
b11111101 "
b11111101 #
#510000
b11111110 "
b11111110 #
#511000
b11111111 "
b11111111 #
#512000
bx !
bx $
b0 "
b0 #
#513000
b0 !
b0 $
b1 "
b1 #
#514000
b1 !
b1 $
b10 "
b10 #
#515000
b11 "
b11 #
#516000
b10 !
b10 $
b100 "
b100 #
#517000
b101 "
b101 #
#518000
b110 "
b110 #
#519000
b111 "
b111 #
#520000
b11 !
b11 $
b1000 "
b1000 #
#521000
b1001 "
b1001 #
#522000
b1010 "
b1010 #
#523000
b1011 "
b1011 #
#524000
b1100 "
b1100 #
#525000
b1101 "
b1101 #
#526000
b1110 "
b1110 #
#527000
b1111 "
b1111 #
#528000
b100 !
b100 $
b10000 "
b10000 #
#529000
b10001 "
b10001 #
#530000
b10010 "
b10010 #
#531000
b10011 "
b10011 #
#532000
b10100 "
b10100 #
#533000
b10101 "
b10101 #
#534000
b10110 "
b10110 #
#535000
b10111 "
b10111 #
#536000
b11000 "
b11000 #
#537000
b11001 "
b11001 #
#538000
b11010 "
b11010 #
#539000
b11011 "
b11011 #
#540000
b11100 "
b11100 #
#541000
b11101 "
b11101 #
#542000
b11110 "
b11110 #
#543000
b11111 "
b11111 #
#544000
b101 !
b101 $
b100000 "
b100000 #
#545000
b100001 "
b100001 #
#546000
b100010 "
b100010 #
#547000
b100011 "
b100011 #
#548000
b100100 "
b100100 #
#549000
b100101 "
b100101 #
#550000
b100110 "
b100110 #
#551000
b100111 "
b100111 #
#552000
b101000 "
b101000 #
#553000
b101001 "
b101001 #
#554000
b101010 "
b101010 #
#555000
b101011 "
b101011 #
#556000
b101100 "
b101100 #
#557000
b101101 "
b101101 #
#558000
b101110 "
b101110 #
#559000
b101111 "
b101111 #
#560000
b110000 "
b110000 #
#561000
b110001 "
b110001 #
#562000
b110010 "
b110010 #
#563000
b110011 "
b110011 #
#564000
b110100 "
b110100 #
#565000
b110101 "
b110101 #
#566000
b110110 "
b110110 #
#567000
b110111 "
b110111 #
#568000
b111000 "
b111000 #
#569000
b111001 "
b111001 #
#570000
b111010 "
b111010 #
#571000
b111011 "
b111011 #
#572000
b111100 "
b111100 #
#573000
b111101 "
b111101 #
#574000
b111110 "
b111110 #
#575000
b111111 "
b111111 #
#576000
b110 !
b110 $
b1000000 "
b1000000 #
#577000
b1000001 "
b1000001 #
#578000
b1000010 "
b1000010 #
#579000
b1000011 "
b1000011 #
#580000
b1000100 "
b1000100 #
#581000
b1000101 "
b1000101 #
#582000
b1000110 "
b1000110 #
#583000
b1000111 "
b1000111 #
#584000
b1001000 "
b1001000 #
#585000
b1001001 "
b1001001 #
#586000
b1001010 "
b1001010 #
#587000
b1001011 "
b1001011 #
#588000
b1001100 "
b1001100 #
#589000
b1001101 "
b1001101 #
#590000
b1001110 "
b1001110 #
#591000
b1001111 "
b1001111 #
#592000
b1010000 "
b1010000 #
#593000
b1010001 "
b1010001 #
#594000
b1010010 "
b1010010 #
#595000
b1010011 "
b1010011 #
#596000
b1010100 "
b1010100 #
#597000
b1010101 "
b1010101 #
#598000
b1010110 "
b1010110 #
#599000
b1010111 "
b1010111 #
#600000
b1011000 "
b1011000 #
#601000
b1011001 "
b1011001 #
#602000
b1011010 "
b1011010 #
#603000
b1011011 "
b1011011 #
#604000
b1011100 "
b1011100 #
#605000
b1011101 "
b1011101 #
#606000
b1011110 "
b1011110 #
#607000
b1011111 "
b1011111 #
#608000
b1100000 "
b1100000 #
#609000
b1100001 "
b1100001 #
#610000
b1100010 "
b1100010 #
#611000
b1100011 "
b1100011 #
#612000
b1100100 "
b1100100 #
#613000
b1100101 "
b1100101 #
#614000
b1100110 "
b1100110 #
#615000
b1100111 "
b1100111 #
#616000
b1101000 "
b1101000 #
#617000
b1101001 "
b1101001 #
#618000
b1101010 "
b1101010 #
#619000
b1101011 "
b1101011 #
#620000
b1101100 "
b1101100 #
#621000
b1101101 "
b1101101 #
#622000
b1101110 "
b1101110 #
#623000
b1101111 "
b1101111 #
#624000
b1110000 "
b1110000 #
#625000
b1110001 "
b1110001 #
#626000
b1110010 "
b1110010 #
#627000
b1110011 "
b1110011 #
#628000
b1110100 "
b1110100 #
#629000
b1110101 "
b1110101 #
#630000
b1110110 "
b1110110 #
#631000
b1110111 "
b1110111 #
#632000
b1111000 "
b1111000 #
#633000
b1111001 "
b1111001 #
#634000
b1111010 "
b1111010 #
#635000
b1111011 "
b1111011 #
#636000
b1111100 "
b1111100 #
#637000
b1111101 "
b1111101 #
#638000
b1111110 "
b1111110 #
#639000
b1111111 "
b1111111 #
#640000
b111 !
b111 $
b10000000 "
b10000000 #
#641000
b10000001 "
b10000001 #
#642000
b10000010 "
b10000010 #
#643000
b10000011 "
b10000011 #
#644000
b10000100 "
b10000100 #
#645000
b10000101 "
b10000101 #
#646000
b10000110 "
b10000110 #
#647000
b10000111 "
b10000111 #
#648000
b10001000 "
b10001000 #
#649000
b10001001 "
b10001001 #
#650000
b10001010 "
b10001010 #
#651000
b10001011 "
b10001011 #
#652000
b10001100 "
b10001100 #
#653000
b10001101 "
b10001101 #
#654000
b10001110 "
b10001110 #
#655000
b10001111 "
b10001111 #
#656000
b10010000 "
b10010000 #
#657000
b10010001 "
b10010001 #
#658000
b10010010 "
b10010010 #
#659000
b10010011 "
b10010011 #
#660000
b10010100 "
b10010100 #
#661000
b10010101 "
b10010101 #
#662000
b10010110 "
b10010110 #
#663000
b10010111 "
b10010111 #
#664000
b10011000 "
b10011000 #
#665000
b10011001 "
b10011001 #
#666000
b10011010 "
b10011010 #
#667000
b10011011 "
b10011011 #
#668000
b10011100 "
b10011100 #
#669000
b10011101 "
b10011101 #
#670000
b10011110 "
b10011110 #
#671000
b10011111 "
b10011111 #
#672000
b10100000 "
b10100000 #
#673000
b10100001 "
b10100001 #
#674000
b10100010 "
b10100010 #
#675000
b10100011 "
b10100011 #
#676000
b10100100 "
b10100100 #
#677000
b10100101 "
b10100101 #
#678000
b10100110 "
b10100110 #
#679000
b10100111 "
b10100111 #
#680000
b10101000 "
b10101000 #
#681000
b10101001 "
b10101001 #
#682000
b10101010 "
b10101010 #
#683000
b10101011 "
b10101011 #
#684000
b10101100 "
b10101100 #
#685000
b10101101 "
b10101101 #
#686000
b10101110 "
b10101110 #
#687000
b10101111 "
b10101111 #
#688000
b10110000 "
b10110000 #
#689000
b10110001 "
b10110001 #
#690000
b10110010 "
b10110010 #
#691000
b10110011 "
b10110011 #
#692000
b10110100 "
b10110100 #
#693000
b10110101 "
b10110101 #
#694000
b10110110 "
b10110110 #
#695000
b10110111 "
b10110111 #
#696000
b10111000 "
b10111000 #
#697000
b10111001 "
b10111001 #
#698000
b10111010 "
b10111010 #
#699000
b10111011 "
b10111011 #
#700000
b10111100 "
b10111100 #
#701000
b10111101 "
b10111101 #
#702000
b10111110 "
b10111110 #
#703000
b10111111 "
b10111111 #
#704000
b11000000 "
b11000000 #
#705000
b11000001 "
b11000001 #
#706000
b11000010 "
b11000010 #
#707000
b11000011 "
b11000011 #
#708000
b11000100 "
b11000100 #
#709000
b11000101 "
b11000101 #
#710000
b11000110 "
b11000110 #
#711000
b11000111 "
b11000111 #
#712000
b11001000 "
b11001000 #
#713000
b11001001 "
b11001001 #
#714000
b11001010 "
b11001010 #
#715000
b11001011 "
b11001011 #
#716000
b11001100 "
b11001100 #
#717000
b11001101 "
b11001101 #
#718000
b11001110 "
b11001110 #
#719000
b11001111 "
b11001111 #
#720000
b11010000 "
b11010000 #
#721000
b11010001 "
b11010001 #
#722000
b11010010 "
b11010010 #
#723000
b11010011 "
b11010011 #
#724000
b11010100 "
b11010100 #
#725000
b11010101 "
b11010101 #
#726000
b11010110 "
b11010110 #
#727000
b11010111 "
b11010111 #
#728000
b11011000 "
b11011000 #
#729000
b11011001 "
b11011001 #
#730000
b11011010 "
b11011010 #
#731000
b11011011 "
b11011011 #
#732000
b11011100 "
b11011100 #
#733000
b11011101 "
b11011101 #
#734000
b11011110 "
b11011110 #
#735000
b11011111 "
b11011111 #
#736000
b11100000 "
b11100000 #
#737000
b11100001 "
b11100001 #
#738000
b11100010 "
b11100010 #
#739000
b11100011 "
b11100011 #
#740000
b11100100 "
b11100100 #
#741000
b11100101 "
b11100101 #
#742000
b11100110 "
b11100110 #
#743000
b11100111 "
b11100111 #
#744000
b11101000 "
b11101000 #
#745000
b11101001 "
b11101001 #
#746000
b11101010 "
b11101010 #
#747000
b11101011 "
b11101011 #
#748000
b11101100 "
b11101100 #
#749000
b11101101 "
b11101101 #
#750000
b11101110 "
b11101110 #
#751000
b11101111 "
b11101111 #
#752000
b11110000 "
b11110000 #
#753000
b11110001 "
b11110001 #
#754000
b11110010 "
b11110010 #
#755000
b11110011 "
b11110011 #
#756000
b11110100 "
b11110100 #
#757000
b11110101 "
b11110101 #
#758000
b11110110 "
b11110110 #
#759000
b11110111 "
b11110111 #
#760000
b11111000 "
b11111000 #
#761000
b11111001 "
b11111001 #
#762000
b11111010 "
b11111010 #
#763000
b11111011 "
b11111011 #
#764000
b11111100 "
b11111100 #
#765000
b11111101 "
b11111101 #
#766000
b11111110 "
b11111110 #
#767000
b11111111 "
b11111111 #
#768000
bx !
bx $
b0 "
b0 #
#769000
b0 !
b0 $
b1 "
b1 #
#770000
b1 !
b1 $
b10 "
b10 #
#771000
b11 "
b11 #
#772000
b10 !
b10 $
b100 "
b100 #
#773000
b101 "
b101 #
#774000
b110 "
b110 #
#775000
b111 "
b111 #
#776000
b11 !
b11 $
b1000 "
b1000 #
#777000
b1001 "
b1001 #
#778000
b1010 "
b1010 #
#779000
b1011 "
b1011 #
#780000
b1100 "
b1100 #
#781000
b1101 "
b1101 #
#782000
b1110 "
b1110 #
#783000
b1111 "
b1111 #
#784000
b100 !
b100 $
b10000 "
b10000 #
#785000
b10001 "
b10001 #
#786000
b10010 "
b10010 #
#787000
b10011 "
b10011 #
#788000
b10100 "
b10100 #
#789000
b10101 "
b10101 #
#790000
b10110 "
b10110 #
#791000
b10111 "
b10111 #
#792000
b11000 "
b11000 #
#793000
b11001 "
b11001 #
