fir.v
module fir (
  input signed [7:0] data_in,
  output signed [17:0] data_out,
  input clk
);

  reg signed [17:0] res = 0;    //регистр для выхода
  reg signed [17:0] temp = 0;   //регистр для счета
  reg [2:0] counter = 0;        //счетчик для массива
  reg [1:0] data_valid = 0;     //флаг, что прошло 10 тактов и пришли данные на вход
  reg signed [7:0] koef[0:2];   //3 коэффициента
  reg signed [7:0] data[0:2];   //последние 3 значения входа
  reg [4:0] takts = 0;          //3 такта на умножение + 1 такт на перенос значения на выход

  assign data_out = res;

  initial begin
    koef[0] = -1;
    koef[1] = 2;
    koef[2] = 3;
    data[0] = 0;
    data[1] = 0;
    data[2] = 0;
  end

  always @(posedge clk) begin
    takts <= takts + 1;
    if (takts == 9) begin
      takts <= 0;
    end
    if (takts == 0) begin
      data_valid <= 1;
      data[2] <= data[1];
      data[1] <= data[0];
      data[0] <= data_in;
      temp <= 0;
    end
    if (data_valid) begin
      if (counter < 3) begin
        temp <= temp + data[counter] * koef[counter];    //когда counter = 3, получим валидный выход
        counter <= counter + 1;
      end
      if (counter == 3) begin
        res <= temp;
        counter <= 0;
        data_valid <= 0;
      end
    end
  end

endmodule

module fir_tb;
  reg signed [7:0] data_in;
  wire signed [17:0] data_out;
  reg clk;

  fir dut (
    .data_in(data_in),
    .data_out(data_out),
    .clk(clk)
  );

  initial begin
    $dumpfile("fir.vcd");
    $dumpvars(0, fir_tb);
    clk = 0;
    forever #5 clk = ~clk;
  end

  initial begin
    for (data_in = -10; data_in <= 10; data_in = data_in + 1) begin
      #100;
    end
    data_in = 0;
    #100;
    $finish;
  end

endmodule

fir.vcd
$date
	Wed Dec 20 12:32:17 2023
$end
$version
	Icarus Verilog
$end
$timescale
	1s
$end
$scope module fir_tb $end
$var wire 18 ! data_out [17:0] $end
$var reg 1 " clk $end
$var reg 8 # data_in [7:0] $end
$scope module dut $end
$var wire 1 " clk $end
$var wire 8 $ data_in [7:0] $end
$var wire 18 % data_out [17:0] $end
$var reg 3 & counter [2:0] $end
$var reg 2 ' data_valid [1:0] $end
$var reg 18 ( res [17:0] $end
$var reg 5 ) takts [4:0] $end
$var reg 18 * temp [17:0] $end
$upscope $end
$upscope $end
$enddefinitions $end
#0
$dumpvars
b0 *
b0 )
b0 (
b0 '
b0 &
b0 %
b11110110 $
b11110110 #
0"
b0 !
$end
#5
b1 '
b1 )
1"
#10
0"
#15
b1 &
b1010 *
b10 )
1"
#20
0"
#25
b10 &
b11 )
1"
#30
0"
#35
b11 &
b100 )
1"
#40
0"
#45
b0 '
b0 &
b1010 !
b1010 %
b1010 (
b101 )
1"
#50
0"
#55
b110 )
1"
#60
0"
#65
b111 )
1"
#70
0"
#75
b1000 )
1"
#80
0"
#85
b1001 )
1"
#90
0"
#95
b0 )
1"
#100
0"
b11110111 #
b11110111 $
#105
b0 *
b1 '
b1 )
1"
#110
0"
#115
b1 &
b1001 *
b10 )
1"
#120
0"
#125
b10 &
b111111111111110101 *
b11 )
1"
#130
0"
#135
b11 &
b100 )
1"
#140
0"
#145
b0 '
b0 &
b111111111111110101 !
b111111111111110101 %
b111111111111110101 (
b101 )
1"
#150
0"
#155
b110 )
1"
#160
0"
#165
b111 )
1"
#170
0"
#175
b1000 )
1"
#180
0"
#185
b1001 )
1"
#190
0"
#195
b0 )
1"
#200
0"
b11111000 #
b11111000 $
#205
b0 *
b1 '
b1 )
1"
#210
0"
#215
b1 &
b1000 *
b10 )
1"
#220
0"
#225
b10 &
b111111111111110110 *
b11 )
1"
#230
0"
#235
b11 &
b111111111111011000 *
b100 )
1"
#240
0"
#245
b0 '
b0 &
b111111111111011000 !
b111111111111011000 %
b111111111111011000 (
b101 )
1"
#250
0"
#255
b110 )
1"
#260
0"
#265
b111 )
1"
#270
0"
#275
b1000 )
1"
#280
0"
#285
b1001 )
1"
#290
0"
#295
b0 )
1"
#300
0"
b11111001 #
b11111001 $
#305
b0 *
b1 '
b1 )
1"
#310
0"
#315
b1 &
b111 *
b10 )
1"
#320
0"
#325
b10 &
b111111111111110111 *
b11 )
1"
#330
0"
#335
b11 &
b111111111111011100 *
b100 )
1"
#340
0"
#345
b0 '
b0 &
b111111111111011100 !
b111111111111011100 %
b111111111111011100 (
b101 )
1"
#350
0"
#355
b110 )
1"
#360
0"
#365
b111 )
1"
#370
0"
#375
b1000 )
1"
#380
0"
#385
b1001 )
1"
#390
0"
#395
b0 )
1"
#400
0"
b11111010 #
b11111010 $
#405
b0 *
b1 '
b1 )
1"
#410
0"
#415
b1 &
b110 *
b10 )
1"
#420
0"
#425
b10 &
b111111111111111000 *
b11 )
1"
#430
0"
#435
b11 &
b111111111111100000 *
b100 )
1"
#440
0"
#445
b0 '
b0 &
b111111111111100000 !
b111111111111100000 %
b111111111111100000 (
b101 )
1"
#450
0"
#455
b110 )
1"
#460
0"
#465
b111 )
1"
#470
0"
#475
b1000 )
1"
#480
0"
#485
b1001 )
1"
#490
0"
#495
b0 )
1"
#500
0"
b11111011 #
b11111011 $
#505
b0 *
b1 '
b1 )
1"
#510
0"
#515
b1 &
b101 *
b10 )
1"
#520
0"
#525
b10 &
b111111111111111001 *
b11 )
1"
#530
0"
#535
b11 &
b111111111111100100 *
b100 )
1"
#540
0"
#545
b0 '
b0 &
b111111111111100100 !
b111111111111100100 %
b111111111111100100 (
b101 )
1"
#550
0"
#555
b110 )
1"
#560
0"
#565
b111 )
1"
#570
0"
#575
b1000 )
1"
#580
0"
#585
b1001 )
1"
#590
0"
#595
b0 )
1"
#600
0"
b11111100 #
b11111100 $
#605
b0 *
b1 '
b1 )
1"
#610
0"
#615
b1 &
b100 *
b10 )
1"
#620
0"
#625
b10 &
b111111111111111010 *
b11 )
1"
#630
0"
#635
b11 &
b111111111111101000 *
b100 )
1"
#640
0"
#645
b0 '
b0 &
b111111111111101000 !
b111111111111101000 %
b111111111111101000 (
b101 )
1"
#650
0"
#655
b110 )
1"
#660
0"
#665
b111 )
1"
#670
0"
#675
b1000 )
1"
#680
0"
#685
b1001 )
1"
#690
0"
#695
b0 )
1"
#700
0"
b11111101 #
b11111101 $
#705
b0 *
b1 '
b1 )
1"
#710
0"
#715
b1 &
b11 *
b10 )
1"
#720
0"
#725
b10 &
b111111111111111011 *
b11 )
1"
#730
0"
#735
b11 &
b111111111111101100 *
b100 )
1"
#740
0"
#745
b0 '
b0 &
b111111111111101100 !
b111111111111101100 %
b111111111111101100 (
b101 )
1"
#750
0"
#755
b110 )
1"
#760
0"
#765
b111 )
1"
#770
0"
#775
b1000 )
1"
#780
0"
#785
b1001 )
1"
#790
0"
#795
b0 )
1"
#800
0"
b11111110 #
b11111110 $
#805
b0 *
b1 '
b1 )
1"
#810
0"
#815
b1 &
b10 *
b10 )
1"
#820
0"
#825
b10 &
b111111111111111100 *
b11 )
1"
#830
0"
#835
b11 &
b111111111111110000 *
b100 )
1"
#840
0"
#845
b0 '
b0 &
b111111111111110000 !
b111111111111110000 %
b111111111111110000 (
b101 )
1"
#850
0"
#855
b110 )
1"
#860
0"
#865
b111 )
1"
#870
0"
#875
b1000 )
1"
#880
0"
#885
b1001 )
1"
#890
0"
#895
b0 )
1"
#900
0"
b11111111 #
b11111111 $
#905
b0 *
b1 '
b1 )
1"
#910
0"
#915
b1 &
b1 *
b10 )
1"
#920
0"
#925
b10 &
b111111111111111101 *
b11 )
1"
#930
0"
#935
b11 &
b111111111111110100 *
b100 )
1"
#940
0"
#945
b0 '
b0 &
b111111111111110100 !
b111111111111110100 %
b111111111111110100 (
b101 )
1"
#950
0"
#955
b110 )
1"
#960
0"
#965
b111 )
1"
#970
0"
#975
b1000 )
1"
#980
0"
#985
b1001 )
1"
#990
0"
#995
b0 )
1"
#1000
0"
b0 #
b0 $
#1005
b0 *
b1 '
b1 )
1"
#1010
0"
#1015
b1 &
b10 )
1"
#1020
0"
#1025
b10 &
b111111111111111110 *
b11 )
1"
#1030
0"
#1035
b11 &
b111111111111111000 *
b100 )
1"
#1040
0"
#1045
b0 '
b0 &
b111111111111111000 !
b111111111111111000 %
b111111111111111000 (
b101 )
1"
#1050
0"
#1055
b110 )
1"
#1060
0"
#1065
b111 )
1"
#1070
0"
#1075
b1000 )
1"
#1080
0"
#1085
b1001 )
1"
#1090
0"
#1095
b0 )
1"
#1100
0"
b1 #
b1 $
#1105
b0 *
b1 '
b1 )
1"
#1110
0"
#1115
b1 &
b111111111111111111 *
b10 )
1"
#1120
0"
#1125
b10 &
b11 )
1"
#1130
0"
#1135
b11 &
b111111111111111100 *
b100 )
1"
#1140
0"
#1145
b0 '
b0 &
b111111111111111100 !
b111111111111111100 %
b111111111111111100 (
b101 )
1"
#1150
0"
#1155
b110 )
1"
#1160
0"
#1165
b111 )
1"
#1170
0"
#1175
b1000 )
1"
#1180
0"
#1185
b1001 )
1"
#1190
0"
#1195
b0 )
1"
#1200
0"
b10 #
b10 $
#1205
b0 *
b1 '
b1 )
1"
#1210
0"
#1215
b1 &
b111111111111111110 *
b10 )
1"
#1220
0"
#1225
b10 &
b0 *
b11 )
1"
#1230
0"
#1235
b11 &
b100 )
1"
#1240
0"
#1245
b0 '
b0 &
b0 !
b0 %
b0 (
b101 )
1"
#1250
0"
#1255
b110 )
1"
#1260
0"
#1265
b111 )
1"
#1270
0"
#1275
b1000 )
1"
#1280
0"
#1285
b1001 )
1"
#1290
0"
#1295
b0 )
1"
#1300
0"
b11 #
b11 $
#1305
b1 '
b1 )
1"
#1310
0"
#1315
b1 &
b111111111111111101 *
b10 )
1"
#1320
0"
#1325
b10 &
b1 *
b11 )
1"
#1330
0"
#1335
b11 &
b100 *
b100 )
1"
#1340
0"
#1345
b0 '
b0 &
b100 !
b100 %
b100 (
b101 )
1"
#1350
0"
#1355
b110 )
1"
#1360
0"
#1365
b111 )
1"
#1370
0"
#1375
b1000 )
1"
#1380
0"
#1385
b1001 )
1"
#1390
0"
#1395
b0 )
1"
#1400
0"
b100 #
b100 $
#1405
b0 *
b1 '
b1 )
1"
#1410
0"
#1415
b1 &
b111111111111111100 *
b10 )
1"
#1420
0"
#1425
b10 &
b10 *
b11 )
1"
#1430
0"
#1435
b11 &
b1000 *
b100 )
1"
#1440
0"
#1445
b0 '
b0 &
b1000 !
b1000 %
b1000 (
b101 )
1"
#1450
0"
#1455
b110 )
1"
#1460
0"
#1465
b111 )
1"
#1470
0"
#1475
b1000 )
1"
#1480
0"
#1485
b1001 )
1"
#1490
0"
#1495
b0 )
1"
#1500
0"
b101 #
b101 $
#1505
b0 *
b1 '
b1 )
1"
#1510
0"
#1515
b1 &
b111111111111111011 *
b10 )
1"
#1520
0"
#1525
b10 &
b11 *
b11 )
1"
#1530
0"
#1535
b11 &
b1100 *
b100 )
1"
#1540
0"
#1545
b0 '
b0 &
b1100 !
b1100 %
b1100 (
b101 )
1"
#1550
0"
#1555
b110 )
1"
#1560
0"
#1565
b111 )
1"
#1570
0"
#1575
b1000 )
1"
#1580
0"
#1585
b1001 )
1"
#1590
0"
#1595
b0 )
1"
#1600
0"
b110 #
b110 $
#1605
b0 *
b1 '
b1 )
1"
#1610
0"
#1615
b1 &
b111111111111111010 *
b10 )
1"
#1620
0"
#1625
b10 &
b100 *
b11 )
1"
#1630
0"
#1635
b11 &
b10000 *
b100 )
1"
#1640
0"
#1645
b0 '
b0 &
b10000 !
b10000 %
b10000 (
b101 )
1"
#1650
0"
#1655
b110 )
1"
#1660
0"
#1665
b111 )
1"
#1670
0"
#1675
b1000 )
1"
#1680
0"
#1685
b1001 )
1"
#1690
0"
#1695
b0 )
1"
#1700
0"
b111 #
b111 $
#1705
b0 *
b1 '
b1 )
1"
#1710
0"
#1715
b1 &
b111111111111111001 *
b10 )
1"
#1720
0"
#1725
b10 &
b101 *
b11 )
1"
#1730
0"
#1735
b11 &
b10100 *
b100 )
1"
#1740
0"
#1745
b0 '
b0 &
b10100 !
b10100 %
b10100 (
b101 )
1"
#1750
0"
#1755
b110 )
1"
#1760
0"
#1765
b111 )
1"
#1770
0"
#1775
b1000 )
1"
#1780
0"
#1785
b1001 )
1"
#1790
0"
#1795
b0 )
1"
#1800
0"
b1000 #
b1000 $
#1805
b0 *
b1 '
b1 )
1"
#1810
0"
#1815
b1 &
b111111111111111000 *
b10 )
1"
#1820
0"
#1825
b10 &
b110 *
b11 )
1"
#1830
0"
#1835
b11 &
b11000 *
b100 )
1"
#1840
0"
#1845
b0 '
b0 &
b11000 !
b11000 %
b11000 (
b101 )
1"
#1850
0"
#1855
b110 )
1"
#1860
0"
#1865
b111 )
1"
#1870
0"
#1875
b1000 )
1"
#1880
0"
#1885
b1001 )
1"
#1890
0"
#1895
b0 )
1"
#1900
0"
b1001 #
b1001 $
#1905
b0 *
b1 '
b1 )
1"
#1910
0"
#1915
b1 &
b111111111111110111 *
b10 )
1"
#1920
0"
#1925
b10 &
b111 *
b11 )
1"
#1930
0"
#1935
b11 &
b11100 *
b100 )
1"
#1940
0"
#1945
b0 '
b0 &
b11100 !
b11100 %
b11100 (
b101 )
1"
#1950
0"
#1955
b110 )
1"
#1960
0"
#1965
b111 )
1"
#1970
0"
#1975
b1000 )
1"
#1980
0"
#1985
b1001 )
1"
#1990
0"
#1995
b0 )
1"
#2000
0"
b1010 #
b1010 $
#2005
b0 *
b1 '
b1 )
1"
#2010
0"
#2015
b1 &
b111111111111110110 *
b10 )
1"
#2020
0"
#2025
b10 &
b1000 *
b11 )
1"
#2030
0"
#2035
b11 &
b100000 *
b100 )
1"
#2040
0"
#2045
b0 '
b0 &
b100000 !
b100000 %
b100000 (
b101 )
1"
#2050
0"
#2055
b110 )
1"
#2060
0"
#2065
b111 )
1"
#2070
0"
#2075
b1000 )
1"
#2080
0"
#2085
b1001 )
1"
#2090
0"
#2095
b0 )
1"
#2100
0"
b0 #
b0 $
#2105
b0 *
b1 '
b1 )
1"
#2110
0"
#2115
b1 &
b10 )
1"
#2120
0"
#2125
b10 &
b10100 *
b11 )
1"
#2130
0"
#2135
b11 &
b101111 *
b100 )
1"
#2140
0"
#2145
b0 '
b0 &
b101111 !
b101111 %
b101111 (
b101 )
1"
#2150
0"
#2155
b110 )
1"
#2160
0"
#2165
b111 )
1"
#2170
0"
#2175
b1000 )
1"
#2180
0"
#2185
b1001 )
1"
#2190
0"
#2195
b0 )
1"
