IIR.v
module iir (
  input signed [7:0] data_in,
  output signed [15:0] data_out,
  input clk
);

  reg signed [15:0] res = 0;
  reg signed [15:0] x0 = 0;
  reg signed [15:0] x1 = 0;
  reg signed [15:0] x2 = 0;
  reg signed [15:0] y0 = 0;
  reg signed [15:0] y1 = 0;
  reg signed [15:0] y2 = 0;

  reg signed [15:0] temp_x0 = 0;
  reg signed [15:0] temp_x1 = 0;
  reg signed [15:0] temp_x2 = 0;
  reg signed [15:0] temp_y0 = 0;
  reg signed [15:0] temp_y1 = 0;
  reg signed [15:0] temp_y2 = 0;

  reg signed [7:0] b = 4;
  reg signed [7:0] a = -1;

  assign data_out = res;

  always @(posedge clk) begin
    // Обновление задержанных значений
    temp_x0 <= data_in;
    temp_x1 <= temp_x0;
    temp_x2 <= temp_x1;
    temp_y0 <= y0;
    temp_y1 <= y1;
    temp_y2 <= y2;

    // Вычисление y(n) с учетом задержек
    y0 <= a * a * a * temp_y2;
    y1 <= a * a * b * temp_x2 + temp_y0;
    y2 <= a * b * temp_x1 + temp_y1;

    // Вычисление x(n) с учетом задержек
    x0 <= b * temp_x0;
    x1 <= b * temp_x1;
    x2 <= b * temp_x2;

    // Обновление итогового значения
    res <= x0 + x1 + x2 + y0;
  end

endmodule

module iir_tb;
  reg signed [7:0] data_in;
  wire signed [15:0] data_out;
  reg clk;

  iir dut (
    .data_in(data_in),
    .data_out(data_out),
    .clk(clk)
  );

  initial begin
    $dumpfile("iir.vcd");
    $dumpvars(0, iir_tb);
    clk = 0;

    forever #5 clk = ~clk;
  end

  initial begin
    // Тестирование для данных от -7 до 7 с шагом 1
    for (data_in = -7; data_in <= 7; data_in = data_in + 1) begin
      #10;
    end
    data_in = 0;
    #100;
    $finish;
  end

endmodule

iir.vcd
$date
	Mon Jun 17 21:57:18 2024
$end
$version
	Icarus Verilog
$end
$timescale
	1s
$end
$scope module iir_tb $end
$var wire 16 ! data_out [15:0] $end
$var reg 1 " clk $end
$var reg 8 # data_in [7:0] $end
$scope module dut $end
$var wire 1 " clk $end
$var wire 8 $ data_in [7:0] $end
$var wire 16 % data_out [15:0] $end
$var reg 8 & a [7:0] $end
$var reg 8 ' b [7:0] $end
$var reg 16 ( res [15:0] $end
$var reg 16 ) temp_x0 [15:0] $end
$var reg 16 * temp_x1 [15:0] $end
$var reg 16 + temp_x2 [15:0] $end
$var reg 16 , temp_y0 [15:0] $end
$var reg 16 - temp_y1 [15:0] $end
$var reg 16 . temp_y2 [15:0] $end
$var reg 16 / x0 [15:0] $end
$var reg 16 0 x1 [15:0] $end
$var reg 16 1 x2 [15:0] $end
$var reg 16 2 y0 [15:0] $end
$var reg 16 3 y1 [15:0] $end
$var reg 16 4 y2 [15:0] $end
$upscope $end
$upscope $end
$enddefinitions $end
#0
$dumpvars
b0 4
b0 3
b0 2
b0 1
b0 0
b0 /
b0 .
b0 -
b0 ,
b0 +
b0 *
b0 )
b0 (
b100 '
b11111111 &
b0 %
b11111001 $
b11111001 #
0"
b0 !
$end
#5
b1111111111111001 )
1"
#10
0"
b11111010 #
b11111010 $
#15
b1111111111100100 /
b1111111111111001 *
b1111111111111010 )
1"
#20
0"
b11111011 #
b11111011 $
#25
b1111111111100100 !
b1111111111100100 %
b1111111111100100 (
b1111111111100100 0
b1111111111101000 /
b11100 4
b1111111111111001 +
b1111111111111010 *
b1111111111111011 )
1"
#30
0"
b11111100 #
b11111100 $
#35
b1111111111001100 !
b1111111111001100 %
b1111111111001100 (
b1111111111100100 1
b1111111111101000 0
b1111111111101100 /
b11000 4
b1111111111100100 3
b11100 .
b1111111111111010 +
b1111111111111011 *
b1111111111111100 )
1"
#40
0"
b11111101 #
b11111101 $
#45
b1111111110111000 !
b1111111110111000 %
b1111111110111000 (
b1111111111101000 1
b1111111111101100 0
b1111111111110000 /
b10100 4
b1111111111101000 3
b1111111111100100 2
b11000 .
b1111111111100100 -
b1111111111111011 +
b1111111111111100 *
b1111111111111101 )
1"
#50
0"
b11111110 #
b11111110 $
#55
b1111111110101000 !
b1111111110101000 %
b1111111110101000 (
b1111111111101100 1
b1111111111110000 0
b1111111111110100 /
b1111111111110100 4
b1111111111101100 3
b1111111111101000 2
b10100 .
b1111111111101000 -
b1111111111100100 ,
b1111111111111100 +
b1111111111111101 *
b1111111111111110 )
1"
#60
0"
b11111111 #
b11111111 $
#65
b1111111110111000 !
b1111111110111000 %
b1111111110111000 (
b1111111111110000 1
b1111111111110100 0
b1111111111111000 /
b1111111111010100 3
b1111111111101100 2
b1111111111110100 .
b1111111111101100 -
b1111111111101000 ,
b1111111111111101 +
b1111111111111110 *
b1111111111111111 )
1"
#70
0"
b0 #
b0 $
#75
b1111111111001000 !
b1111111111001000 %
b1111111111001000 (
b1111111111110100 1
b1111111111111000 0
b1111111111111100 /
b1111111111011100 3
b1100 2
b1111111111010100 -
b1111111111101100 ,
b1111111111111110 +
b1111111111111111 *
b0 )
1"
#80
0"
b1 #
b1 $
#85
b1111111111110100 !
b1111111111110100 %
b1111111111110100 (
b1111111111111000 1
b1111111111111100 0
b0 /
b1111111111011000 4
b1111111111100100 3
b1111111111011100 -
b1100 ,
b1111111111111111 +
b0 *
b1 )
1"
#90
0"
b10 #
b10 $
#95
b0 !
b0 %
b0 (
b1111111111111100 1
b0 0
b100 /
b1111111111011100 4
b1000 3
b1111111111011000 .
b1111111111100100 -
b0 +
b1 *
b10 )
1"
#100
0"
b11 #
b11 $
#105
b1100 !
b1100 %
b1100 (
b0 1
b100 0
b1000 /
b1111111111100000 4
b1100 3
b101000 2
b1111111111011100 .
b1000 -
b1 +
b10 *
b11 )
1"
#110
0"
b100 #
b100 $
#115
b110100 !
b110100 %
b110100 (
b100 1
b1000 0
b1100 /
b0 4
b10000 3
b100100 2
b1111111111100000 .
b1100 -
b101000 ,
b10 +
b11 *
b100 )
1"
#120
0"
b101 #
b101 $
#125
b111100 !
b111100 %
b111100 (
b1000 1
b1100 0
b10000 /
b110000 3
b100000 2
b0 .
b10000 -
b100100 ,
b11 +
b100 *
b101 )
1"
#130
0"
b110 #
b110 $
#135
b1000100 !
b1000100 %
b1000100 (
b1100 1
b10000 0
b10100 /
b0 2
b110000 -
b100000 ,
b100 +
b101 *
b110 )
1"
#140
0"
b111 #
b111 $
#145
b110000 !
b110000 %
b110000 (
b10000 1
b10100 0
b11000 /
b11100 4
b0 ,
b101 +
b110 *
b111 )
1"
#150
0"
b0 #
b0 $
#155
b111100 !
b111100 %
b111100 (
b10100 1
b11000 0
b11100 /
b11000 4
b10100 3
b11100 .
b110 +
b111 *
b0 )
1"
#160
0"
#165
b1001000 !
b1001000 %
b1001000 (
b11000 1
b11100 0
b0 /
b10100 4
b11000 3
b1111111111100100 2
b11000 .
b10100 -
b111 +
b0 *
1"
#170
0"
#175
b11000 !
b11000 %
b11000 (
b11100 1
b0 0
b11100 3
b1111111111101000 2
b10100 .
b11000 -
b1111111111100100 ,
b0 +
1"
#180
0"
#185
b100 !
b100 %
b100 (
b0 1
b11000 4
b1111111111100100 3
b1111111111101100 2
b11100 -
b1111111111101000 ,
1"
#190
0"
#195
b1111111111101100 !
b1111111111101100 %
b1111111111101100 (
b11100 4
b1111111111101000 3
b11000 .
b1111111111100100 -
b1111111111101100 ,
1"
#200
0"
#205
b1111111111100100 4
b1111111111101100 3
b1111111111101000 2
b11100 .
b1111111111101000 -
1"
#210
0"
#215
b1111111111101000 !
b1111111111101000 %
b1111111111101000 (
b1111111111101000 4
b1111111111100100 2
b1111111111100100 .
b1111111111101100 -
b1111111111101000 ,
1"
#220
0"
#225
b1111111111100100 !
b1111111111100100 %
b1111111111100100 (
b1111111111101100 4
b1111111111101000 3
b11100 2
b1111111111101000 .
b1111111111100100 ,
1"
#230
0"
#235
b11100 !
b11100 %
b11100 (
b1111111111100100 3
b11000 2
b1111111111101100 .
b1111111111101000 -
b11100 ,
1"
#240
0"
#245
b11000 !
b11000 %
b11000 (
b1111111111101000 4
b11100 3
b10100 2
b1111111111100100 -
b11000 ,
1"
