task10/task10.v
`timescale 1ns / 1ps

module task10 #(parameter WIDTH = 8, parameter NUM = 4)(
        input clk_in,
        input [WIDTH-1:0] data_in,
        output [NUM-1:0][WIDTH-1:0] out,
        output [NUM-1:0] out_valid
    );

    reg [NUM-1:0][WIDTH-1:0] data = 'h0;
    reg [NUM-1:0] data_valid = 'h0;

    assign out = data;
    assign out_valid = data_valid;

    genvar i;
    integer j;

    wire [NUM-1:0] comp_mask;
    wire [NUM-1:0] data_mask;
    wire [NUM-1:0] shift_mask;

    assign data_mask = comp_mask ? comp_mask - 1 : comp_mask;
    assign shift_mask = data_mask ? data_mask : {NUM{1'b1}};
    generate
        for (i = 0; i < NUM; i = i + 1) 
            assign comp_mask[i] = (data[i] == data_in) & data_valid[i];
    endgenerate
    
    always@(posedge clk_in) begin
        for (j = 1; j < NUM; j = j + 1) begin 
            data[j] <= (shift_mask[j - 1]) ? data[j - 1] : data[j]; 
        end
        data[0] <= data_in;
         
        data_valid <= (data_mask) ? data_valid : (data_valid << 1) | 4'b1; 
    end
endmodule

module task10_tb();
    localparam WIDTH = 8, NUM = 4;
    reg clk_in = 'b0;
    reg [WIDTH-1:0] data_in = 'h0;
    wire [NUM-1:0][WIDTH-1:0] out;
    wire [NUM-1:0] out_valid;

    task10 #(.WIDTH(WIDTH), .NUM(NUM)) test_module (
        .clk_in(clk_in),
        .data_in(data_in),
        .out(out),
        .out_valid(out_valid)
    );
    
    integer i;
    always #5 clk_in = ~clk_in;

    initial begin
        $dumpfile("task10.vcd");
        $dumpvars(0, task10_tb);
        data_in = 'b0;
        for (i = 0; i < 3; i = i + 1)
            #10 data_in = data_in + 1;
        data_in = 'b1;
        for (i = 0; i < 40-3; i = i + 1)
            #10 data_in = ((data_in) % 4) + 1;
        $finish;
    end

endmodule

task10/task10.vcd
$date
	Wed Jun 19 22:27:55 2024
$end
$version
	Icarus Verilog
$end
$timescale
	1ps
$end
$scope module task10_tb $end
$var wire 4 ! out_valid [3:0] $end
$var wire 32 " out [31:0] $end
$var reg 1 # clk_in $end
$var reg 8 $ data_in [7:0] $end
$var integer 32 % i [31:0] $end
$scope module test_module $end
$var wire 1 # clk_in $end
$var wire 8 & data_in [7:0] $end
$var wire 32 ' out [31:0] $end
$var wire 4 ( out_valid [3:0] $end
$var wire 4 ) shift_mask [3:0] $end
$var wire 4 * data_mask [3:0] $end
$var wire 4 + comp_mask [3:0] $end
$var reg 32 , data [31:0] $end
$var reg 4 - data_valid [3:0] $end
$var integer 32 . j [31:0] $end
$scope begin genblk1[0] $end
$upscope $end
$scope begin genblk1[1] $end
$upscope $end
$scope begin genblk1[2] $end
$upscope $end
$scope begin genblk1[3] $end
$upscope $end
$upscope $end
$upscope $end
$enddefinitions $end
#0
$dumpvars
bx .
b0 -
b0 ,
b0 +
b0 *
b1111 )
b0 (
b0 '
b0 &
b0 %
b0 $
0#
b0 "
b0 !
$end
#5000
b1 +
b1 !
b1 (
b1 -
b100 .
1#
#10000
b0 +
0#
b1 %
b1 $
b1 &
#15000
b1 +
b11 !
b11 (
b11 -
b1 "
b1 '
b1 ,
b100 .
1#
#20000
b0 +
0#
b10 %
b10 $
b10 &
#25000
b1 +
b111 !
b111 (
b111 -
b100000010 "
b100000010 '
b100000010 ,
b100 .
1#
#30000
b1 )
b1 *
b10 +
0#
b0 %
b1 $
b1 &
#35000
b1111 )
b0 *
b1 +
b1000000001 "
b1000000001 '
b1000000001 ,
b100 .
1#
#40000
b1 )
b1 *
b10 +
0#
b1 %
b10 $
b10 &
#45000
b1111 )
b0 *
b1 +
b100000010 "
b100000010 '
b100000010 ,
b100 .
1#
#50000
b0 +
0#
b10 %
b11 $
b11 &
#55000
b1 +
b1111 !
b1111 (
b1111 -
b10000001000000011 "
b10000001000000011 '
b10000001000000011 ,
b100 .
1#
#60000
b0 +
0#
b11 %
b100 $
b100 &
#65000
b1 +
b1000000100000001100000100 "
b1000000100000001100000100 '
b1000000100000001100000100 ,
b100 .
1#
#70000
b111 )
b111 *
b1000 +
0#
b100 %
b1 $
b1 &
#75000
b1111 )
b0 *
b1 +
b10000000110000010000000001 "
b10000000110000010000000001 '
b10000000110000010000000001 ,
b100 .
1#
#80000
b111 )
b111 *
b1000 +
0#
b101 %
b10 $
b10 &
#85000
b1111 )
b0 *
b1 +
b11000001000000000100000010 "
b11000001000000000100000010 '
b11000001000000000100000010 ,
b100 .
1#
#90000
b111 )
b111 *
b1000 +
0#
b110 %
b11 $
b11 &
#95000
b1111 )
b0 *
b1 +
b100000000010000001000000011 "
b100000000010000001000000011 '
b100000000010000001000000011 ,
b100 .
1#
#100000
b111 )
b111 *
b1000 +
0#
b111 %
b100 $
b100 &
#105000
b1111 )
b0 *
b1 +
b1000000100000001100000100 "
b1000000100000001100000100 '
b1000000100000001100000100 ,
b100 .
1#
#110000
b111 )
b111 *
b1000 +
0#
b1000 %
b1 $
b1 &
#115000
b1111 )
b0 *
b1 +
b10000000110000010000000001 "
b10000000110000010000000001 '
b10000000110000010000000001 ,
b100 .
1#
#120000
b111 )
b111 *
b1000 +
0#
b1001 %
b10 $
b10 &
#125000
b1111 )
b0 *
b1 +
b11000001000000000100000010 "
b11000001000000000100000010 '
b11000001000000000100000010 ,
b100 .
1#
#130000
b111 )
b111 *
b1000 +
0#
b1010 %
b11 $
b11 &
#135000
b1111 )
b0 *
b1 +
b100000000010000001000000011 "
b100000000010000001000000011 '
b100000000010000001000000011 ,
b100 .
1#
#140000
b111 )
b111 *
b1000 +
0#
b1011 %
b100 $
b100 &
#145000
b1111 )
b0 *
b1 +
b1000000100000001100000100 "
b1000000100000001100000100 '
b1000000100000001100000100 ,
b100 .
1#
#150000
b111 )
b111 *
b1000 +
0#
b1100 %
b1 $
b1 &
#155000
b1111 )
b0 *
b1 +
b10000000110000010000000001 "
b10000000110000010000000001 '
b10000000110000010000000001 ,
b100 .
1#
#160000
b111 )
b111 *
b1000 +
0#
b1101 %
b10 $
b10 &
#165000
b1111 )
b0 *
b1 +
b11000001000000000100000010 "
b11000001000000000100000010 '
b11000001000000000100000010 ,
b100 .
1#
#170000
b111 )
b111 *
b1000 +
0#
b1110 %
b11 $
b11 &
#175000
b1111 )
b0 *
b1 +
b100000000010000001000000011 "
b100000000010000001000000011 '
b100000000010000001000000011 ,
b100 .
1#
#180000
b111 )
b111 *
b1000 +
0#
b1111 %
b100 $
b100 &
#185000
b1111 )
b0 *
b1 +
b1000000100000001100000100 "
b1000000100000001100000100 '
b1000000100000001100000100 ,
b100 .
1#
#190000
b111 )
b111 *
b1000 +
0#
b10000 %
b1 $
b1 &
#195000
b1111 )
b0 *
b1 +
b10000000110000010000000001 "
b10000000110000010000000001 '
b10000000110000010000000001 ,
b100 .
1#
#200000
b111 )
b111 *
b1000 +
0#
b10001 %
b10 $
b10 &
#205000
b1111 )
b0 *
b1 +
b11000001000000000100000010 "
b11000001000000000100000010 '
b11000001000000000100000010 ,
b100 .
1#
#210000
b111 )
b111 *
b1000 +
0#
b10010 %
b11 $
b11 &
#215000
b1111 )
b0 *
b1 +
b100000000010000001000000011 "
b100000000010000001000000011 '
b100000000010000001000000011 ,
b100 .
1#
#220000
b111 )
b111 *
b1000 +
0#
b10011 %
b100 $
b100 &
#225000
b1111 )
b0 *
b1 +
b1000000100000001100000100 "
b1000000100000001100000100 '
b1000000100000001100000100 ,
b100 .
1#
#230000
b111 )
b111 *
b1000 +
0#
b10100 %
b1 $
b1 &
#235000
b1111 )
b0 *
b1 +
b10000000110000010000000001 "
b10000000110000010000000001 '
b10000000110000010000000001 ,
b100 .
1#
#240000
b111 )
b111 *
b1000 +
0#
b10101 %
b10 $
b10 &
#245000
b1111 )
b0 *
b1 +
b11000001000000000100000010 "
b11000001000000000100000010 '
b11000001000000000100000010 ,
b100 .
1#
#250000
b111 )
b111 *
b1000 +
0#
b10110 %
b11 $
b11 &
#255000
b1111 )
b0 *
b1 +
b100000000010000001000000011 "
b100000000010000001000000011 '
b100000000010000001000000011 ,
b100 .
1#
#260000
b111 )
b111 *
b1000 +
0#
b10111 %
b100 $
b100 &
#265000
b1111 )
b0 *
b1 +
b1000000100000001100000100 "
b1000000100000001100000100 '
b1000000100000001100000100 ,
b100 .
1#
#270000
b111 )
b111 *
b1000 +
0#
b11000 %
b1 $
b1 &
#275000
b1111 )
b0 *
b1 +
b10000000110000010000000001 "
b10000000110000010000000001 '
b10000000110000010000000001 ,
b100 .
1#
#280000
b111 )
b111 *
b1000 +
0#
b11001 %
b10 $
b10 &
#285000
b1111 )
b0 *
b1 +
b11000001000000000100000010 "
b11000001000000000100000010 '
b11000001000000000100000010 ,
b100 .
1#
#290000
b111 )
b111 *
b1000 +
0#
b11010 %
b11 $
b11 &
#295000
b1111 )
b0 *
b1 +
b100000000010000001000000011 "
b100000000010000001000000011 '
b100000000010000001000000011 ,
b100 .
1#
#300000
b111 )
b111 *
b1000 +
0#
b11011 %
b100 $
b100 &
#305000
b1111 )
b0 *
b1 +
b1000000100000001100000100 "
b1000000100000001100000100 '
b1000000100000001100000100 ,
b100 .
1#
#310000
b111 )
b111 *
b1000 +
0#
b11100 %
b1 $
b1 &
#315000
b1111 )
b0 *
b1 +
b10000000110000010000000001 "
b10000000110000010000000001 '
b10000000110000010000000001 ,
b100 .
1#
#320000
b111 )
b111 *
b1000 +
0#
b11101 %
b10 $
b10 &
#325000
b1111 )
b0 *
b1 +
b11000001000000000100000010 "
b11000001000000000100000010 '
b11000001000000000100000010 ,
b100 .
1#
#330000
b111 )
b111 *
b1000 +
0#
b11110 %
b11 $
b11 &
#335000
b1111 )
b0 *
b1 +
b100000000010000001000000011 "
b100000000010000001000000011 '
b100000000010000001000000011 ,
b100 .
1#
#340000
b111 )
b111 *
b1000 +
0#
b11111 %
b100 $
b100 &
#345000
b1111 )
b0 *
b1 +
b1000000100000001100000100 "
b1000000100000001100000100 '
b1000000100000001100000100 ,
b100 .
1#
#350000
b111 )
b111 *
b1000 +
0#
b100000 %
b1 $
b1 &
#355000
b1111 )
b0 *
b1 +
b10000000110000010000000001 "
b10000000110000010000000001 '
b10000000110000010000000001 ,
b100 .
1#
#360000
b111 )
b111 *
b1000 +
0#
b100001 %
b10 $
b10 &
#365000
b1111 )
b0 *
b1 +
b11000001000000000100000010 "
b11000001000000000100000010 '
b11000001000000000100000010 ,
b100 .
1#
#370000
b111 )
b111 *
b1000 +
0#
b100010 %
b11 $
b11 &
#375000
b1111 )
b0 *
b1 +
b100000000010000001000000011 "
b100000000010000001000000011 '
b100000000010000001000000011 ,
b100 .
1#
#380000
b111 )
b111 *
b1000 +
0#
b100011 %
b100 $
b100 &
#385000
b1111 )
b0 *
b1 +
b1000000100000001100000100 "
b1000000100000001100000100 '
b1000000100000001100000100 ,
b100 .
1#
#390000
b111 )
b111 *
b1000 +
0#
b100100 %
b1 $
b1 &
#395000
b1111 )
b0 *
b1 +
b10000000110000010000000001 "
b10000000110000010000000001 '
b10000000110000010000000001 ,
b100 .
1#
#400000
b111 )
b111 *
b1000 +
0#
b100101 %
b10 $
b10 &
